Workbook

Sheet Assumptions
B2: #VALUE! | F2: IRR | G2: =Schedules!M2 -> 0.1957715 | I2: blue = hardcodes ; black = formulas ; green = off-sheet references ; red = external links/sources ; purple = sensitivity analysis levers
B3: $ millions except for share-related numbers | F3: MoIC | G3: =Schedules!M3 -> 2.4447868
B5: General Assumptions
B7: Holding period (yrs) | C7: 5
B9: Previous close stock price | C9: {=_FV(B2,"price",TRUE)} -> 46.62
B10: Current shares outstanding (m) | C10: {=_FV(B2,"Shares outstanding",TRUE)/1000000} -> 115.9543
B12: Purchase premium above market | C12: 0.15
B14: Entry multiple (EV / revenue) | C14: =C20/C16 -> 6.0691472
B16: 2024A revenue | C16: ='Financial Statements'!E84 -> 964
B17: Purchase price | C17: =C9*C10*(1+C12) -> 6216.6579
B18: - Debt | C18: 0
B19: - Cash | C19: ='Financial Statements'!L10 -> 366
B20: Enterprise value | C20: =C17-C19 -> 5850.6579
B22: Minimum cash | C22: 100
B24: M&A fee - % of purchase price | C24: 0.01
B25: M&A fee - $ | C25: =C24*C17 -> 62.166579
B27: Tax rate | C27: 0.21
B29: Sponsor ownership | C29: 0.9
B30: Management rollover | C30: =1-C29 -> 0.1
B31: Management options | C31: 0.1
B34: Debt Assumptions
B36: Tranch | C36: x Revenue | D36: $ Value | E36: % Cash Int. | F36: % PIK Int. | G36: % Amort. | H36: Prin. Repay. | I36: Max Draw | J36: Commitment | K36: % Com. Fee | L36: Lockup Per. | M36: % Fin. Fee
B37: Revolver | C37: 0.5 | D37: =C37*C16 -> 482 | E37: ='Loan Terms Derivation'!C8 -> 0.0624 | J37: =D37*2 -> 964 | K37: ='Loan Terms Derivation'!C10 -> 0.0075
B38: Term loan A | C38: 1 | D38: =C38*C16 -> 964 | E38: ='Loan Terms Derivation'!C16 -> 0.066 | H38: ='Loan Terms Derivation'!C20 -> 192.8 | I38: =D38*1.5 -> 1446 | M38: 0.01
B39: Term loan B | C39: 2 | D39: =C39*C16 -> 1928 | E39: ='Loan Terms Derivation'!C26 -> 0.066 | G39: ='Loan Terms Derivation'!C28 -> 0.02 | I39: =D39*1.5 -> 2892 | M39: 0.01
B40: High yield | C40: 1 | D40: =C40*C16 -> 964 | E40: ='Loan Terms Derivation'!C34 -> 0.096 | I40: =D40*1.5 -> 1446 | L40: 2 | M40: 0.02
B41: Mezzanine | C41: 0.5 | D41: =C41*C16 -> 482 | E41: ='Loan Terms Derivation'!C41 -> 0.1149 | F41: ='Loan Terms Derivation'!C40 -> 0.02 | I41: =D41*3 -> 1446 | M41: 0.02
B43: Financing fee - useful life | C43: 10
B45: Interest as % of average balance | C45: Yes
B47: Purchase Accounting Assumptions
B49: Excess allocated to goodwill | C49: 0.9
B50: Excess allocated to PP&E | C50: 0.1
B51: Life of incremental PP&E | C51: 10

Sheet Sources & Uses
B2: CAVA Group, Inc.
B3: $ millions
B5: Sources and Uses
B7: Amount of equity required | C7: =C18-SUM(C11:C15) -> 1516.6645
B9: Sources
B11: Revolver | C11: =Assumptions!D37 -> 482
B12: TLA | C12: =Assumptions!D38 -> 964
B13: TLB | C13: =Assumptions!D39 -> 1928
B14: High yield | C14: =Assumptions!D40 -> 964
B15: Mezz | C15: =Assumptions!D41 -> 482
B16: Sponsor equity | C16: ='Sources & Uses'!C7*Assumptions!C29 -> 1364.998
B17: Management rollover | C17: ='Sources & Uses'!C7*Assumptions!C30 -> 151.66645
B18: Total sources | C18: =C26 -> 6336.6645
B20: Uses
B22: Refinance existing debt | C22: 0
B23: M&A fee | C23: =Assumptions!C25 -> 62.166579
B24: Financing fees | C24: =Assumptions!M38*Assumptions!D38+Assumptions!M39*Assumptions!D39+Assumptions!M41*Assumptions!D40+Assumptions!M40*Assumptions!D41 -> 57.84
B25: Purchase price | C25: =Assumptions!C17 -> 6216.6579
B26: Total uses | C26: =SUM(C22:C25) -> 6336.6645

Sheet Financial Statements
B2: CAVA Group, Inc.
B3: $ millions
C4: 2022 | D4: 2023 | E4: 2024 | F4: 2025 | G4: 2026 | H4: 2027 | I4: 2028 | J4: 2029
B6: Balance Sheet
M8: 2024A
B9: Assets | L9: Actual | M9: Adjustment | N9: Adjusted
B10: Cash and equivalents | C10: 39 | D10: 332 | E10: =N10 -> 100 | F10: =Schedules!F208 -> 100 | G10: =Schedules!G208 -> 100 | H10: =Schedules!H208 -> 100 | I10: =Schedules!I208 -> 100 | J10: =Schedules!J208 -> 100 | L10: 366 | M10: =Assumptions!C22-L10 -> -266 | N10: =M10+L10 -> 100
B11: Accounts receivable | C11: 8 | D11: 12 | E11: =N11 -> 13 | F11: =Schedules!F76 -> 16.51705 | G11: =Schedules!G76 -> 20.560879 | H11: =Schedules!H76 -> 24.967799 | I11: =Schedules!I76 -> 29.682686 | J11: =Schedules!J76 -> 34.977419 | L11: 13 | M11: 0 | N11: =M11+L11 -> 13
B12: Inventories | C12: 5 | D12: 6 | E12: =N12 -> 8 | F12: =Schedules!F77 -> 9.7129724 | G12: =Schedules!G77 -> 11.860203 | H12: =Schedules!H77 -> 14.13537 | I12: =Schedules!I77 -> 16.502494 | J12: =Schedules!J77 -> 19.107045 | L12: 8 | M12: 0 | N12: =M12+L12 -> 8
B13: Prepaid expenses | C13: 6 | D13: 5 | E13: =N13 -> 7 | F13: =$E$13 -> 7 | G13: =$E$13 -> 7 | H13: =$E$13 -> 7 | I13: =$E$13 -> 7 | J13: =$E$13 -> 7 | L13: 7 | M13: 0 | N13: =M13+L13 -> 7
B14: Total current assets | C14: =SUM(C10:C13) -> 58 | D14: =SUM(D10:D13) -> 355 | E14: =N14 -> 128 | F14: =SUM(F10:F13) -> 133.23002 | G14: =SUM(G10:G13) -> 139.42108 | H14: =SUM(H10:H13) -> 146.10317 | I14: =SUM(I10:I13) -> 153.18518 | J14: =SUM(J10:J13) -> 161.08446 | L14: =SUM(L10:L13) -> 394 | N14: =SUM(N10:N13) -> 128
B16: PP&E | C16: 243 | D16: 331 | E16: =N16 -> 970.42844 | F16: =Schedules!F120 -> 943.22985 | G16: =Schedules!G120 -> 953.28503 | H16: =Schedules!H120 -> 978.47736 | I16: =Schedules!I120 -> 1016.5363 | J16: =Schedules!J120 -> 1065.5318 | L16: 373 | M16: =Schedules!C13 -> 597.42844 | N16: =L16+M16 -> 970.42844
B17: Operating lease assets | C17: 273 | D17: 289 | E17: =N17 -> 322 | F17: =$E$17 -> 322 | G17: =$E$17 -> 322 | H17: =$E$17 -> 322 | I17: =$E$17 -> 322 | J17: =$E$17 -> 322 | L17: 322 | M17: 0 | N17: =L17+M17 -> 322
B18: Goodwill | C18: 2 | D18: 2 | E18: =N18 -> 5378.856 | F18: =$E$18 -> 5378.856 | G18: =$E$18 -> 5378.856 | H18: =$E$18 -> 5378.856 | I18: =$E$18 -> 5378.856 | J18: =$E$18 -> 5378.856 | L18: 2 | M18: =Schedules!C12 -> 5376.856 | N18: =L18+M18 -> 5378.856
B19: Intangibles | C19: 1 | D19: 1 | E19: =N19 -> 1 | F19: =$E$19 -> 1 | G19: =$E$19 -> 1 | H19: =$E$19 -> 1 | I19: =$E$19 -> 1 | J19: =$E$19 -> 1 | L19: 1 | M19: 0 | N19: =L19+M19 -> 1
B20: Deferred income taxes | C20: 0 | D20: 0 | E20: =N20 -> 72 | F20: ='Tax Schedules '!F24 -> 53.596913 | G20: ='Tax Schedules '!G24 -> 146.11257 | H20: ='Tax Schedules '!H24 -> 230.69094 | I20: ='Tax Schedules '!I24 -> 331.25769 | J20: ='Tax Schedules '!J24 -> 432.17185 | L20: 72 | M20: 0 | N20: =L20+M20 -> 72
B21: Other long-term assets | C21: 6 | D21: 5 | E21: =N21 -> 6 | F21: =$E$21 -> 6 | G21: =$E$21 -> 6 | H21: =$E$21 -> 6 | I21: =$E$21 -> 6 | J21: =$E$21 -> 6 | L21: 6 | M21: 0 | N21: =L21+M21 -> 6
B22: Financing fees | C22: 0 | D22: 0 | E22: =N22 -> 57.84 | F22: =Schedules!F112 -> 52.056 | G22: =Schedules!G112 -> 46.272 | H22: =Schedules!H112 -> 40.488 | I22: =Schedules!I112 -> 34.704 | J22: =Schedules!J112 -> 28.92 | L22: 0 | M22: ='Sources & Uses'!C24 -> 57.84 | N22: =L22+M22 -> 57.84
B23: Total non-current assets | C23: =SUM(C16:C22) -> 525 | D23: =SUM(D16:D22) -> 628 | E23: =SUM(E16:E22) -> 6808.1244 | F23: =SUM(F16:F22) -> 6756.7388 | G23: =SUM(G16:G22) -> 6853.5256 | H23: =SUM(H16:H22) -> 6957.5123 | I23: =SUM(I16:I22) -> 7090.3539 | J23: =SUM(J16:J22) -> 7234.4796 | L23: =SUM(L16:L22) -> 776 | N23: =SUM(N16:N22) -> 6808.1244
B25: Total assets | C25: =C23+C14 -> 583 | D25: =D23+D14 -> 983 | E25: =E23+E14 -> 6936.1244 | F25: =F23+F14 -> 6889.9688 | G25: =G23+G14 -> 6992.9467 | H25: =H23+H14 -> 7103.6155 | I25: =I23+I14 -> 7243.5391 | J25: =J23+J14 -> 7395.5641 | L25: =L23+L14 -> 1170 | M25: =SUM(M16:M22,M10:M13) -> 5766.1244 | N25: =N23+N14 -> 6936.1244
B27: Liabilities
B28: Accounts payable | C28: 14 | D28: 17 | E28: =N28 -> 26 | F28: =Schedules!F80 -> 31.56716 | G28: =Schedules!G80 -> 38.545659 | H28: =Schedules!H80 -> 45.939953 | I28: =Schedules!I80 -> 53.633105 | J28: =Schedules!J80 -> 62.097897 | L28: 26 | M28: 0 | N28: =L28+M28 -> 26
B29: Accrued expenses | C29: 40 | D29: 59 | E29: =N29 -> 70 | F29: =Schedules!F81 -> 88.694959 | G29: =Schedules!G81 -> 110.40993 | H29: =Schedules!H81 -> 134.07466 | I29: =Schedules!I81 -> 159.82985 | J29: =Schedules!J81 -> 187.82536 | L29: 70 | M29: 0 | N29: =L29+M29 -> 70
B30: Operating lease liabilities | C30: 30 | D30: 33 | E30: =N30 -> 37 | F30: =$E$30 -> 37 | G30: =$E$30 -> 37 | H30: =$E$30 -> 37 | I30: =$E$30 -> 37 | J30: =$E$30 -> 37 | L30: 37 | M30: 0 | N30: =L30+M30 -> 37
B31: Total current liabilities | C31: =SUM(C28:C30) -> 84 | D31: =SUM(D28:D30) -> 109 | E31: =SUM(E28:E30) -> 133 | F31: =SUM(F28:F30) -> 157.26212 | G31: =SUM(G28:G30) -> 185.95559 | H31: =SUM(H28:H30) -> 217.01462 | I31: =SUM(I28:I30) -> 250.46295 | J31: =SUM(J28:J30) -> 286.92325 | L31: =SUM(L28:L30) -> 133 | N31: =SUM(N28:N30) -> 133
B33: Deferred income taxes | C33: 0 | D33: 0 | E33: =N33 -> 125.45997 | F33: ='Tax Schedules '!F25 -> 0 | G33: ='Tax Schedules '!G25 -> 0 | H33: ='Tax Schedules '!H25 -> 0 | I33: ='Tax Schedules '!I25 -> 0 | J33: ='Tax Schedules '!J25 -> 0 | L33: 0 | M33: =Schedules!C15 -> 125.45997 | N33: =L33+M33 -> 125.45997
B34: Operating lease liabilities | C34: 286 | D34: 304 | E34: =N34 -> 341 | F34: =$E$34 -> 341 | G34: =$E$34 -> 341 | H34: =$E$34 -> 341 | I34: =$E$34 -> 341 | J34: =$E$34 -> 341 | L34: 341 | M34: 0 | N34: =L34+M34 -> 341
B35: Other long-term liabilities | C35: 0 | D35: 0 | E35: =N35 -> 0 | F35: =$E$35 -> 0 | G35: =$E$35 -> 0 | H35: =$E$35 -> 0 | I35: =$E$35 -> 0 | J35: =$E$35 -> 0 | L35: 0 | M35: 0 | N35: =L35+M35 -> 0
B36: Revolver | C36: 0 | D36: 0 | E36: =N36 -> 482 | F36: =Schedules!F135 -> 964 | G36: =Schedules!G135 -> 964 | H36: =Schedules!H135 -> 964 | I36: =Schedules!I135 -> 964 | J36: =Schedules!J135 -> 964 | L36: 0 | M36: ='Sources & Uses'!C11 -> 482 | N36: =L36+M36 -> 482
B37: TLA | C37: 0 | D37: 0 | E37: =N37 -> 964 | F37: =Schedules!F156 -> 861.57764 | G37: =Schedules!G156 -> 668.77764 | H37: =Schedules!H156 -> 475.97764 | I37: =Schedules!I156 -> 283.17764 | J37: =Schedules!J156 -> 90.377644 | L37: 0 | M37: ='Sources & Uses'!C12 -> 964 | N37: =L37+M37 -> 964
B38: TLB | C38: 0 | D38: 0 | E38: =N38 -> 1928 | F38: =Schedules!F171 -> 1889.44 | G38: =Schedules!G171 -> 2391.2858 | H38: =Schedules!H171 -> 2837.3547 | I38: =Schedules!I171 -> 2835.2529 | J38: =Schedules!J171 -> 2835.2949 | L38: 0 | M38: ='Sources & Uses'!C13 -> 1928 | N38: =L38+M38 -> 1928
B39: High yield | C39: 0 | D39: 0 | E39: =N39 -> 964 | F39: =Schedules!F185 -> 964 | G39: =Schedules!G185 -> 964 | H39: =Schedules!H185 -> 964 | I39: =Schedules!I185 -> 1369.5095 | J39: =Schedules!J185 -> 1446 | L39: 0 | M39: ='Sources & Uses'!C14 -> 964 | N39: =L39+M39 -> 964
B40: Mezz | C40: 0 | D40: 0 | E40: =N40 -> 482 | F40: =Schedules!F200 -> 491.64 | G40: =Schedules!G200 -> 501.4728 | H40: =Schedules!H200 -> 511.50226 | I40: =Schedules!I200 -> 521.7323 | J40: =Schedules!J200 -> 789.82891 | L40: 0 | M40: ='Sources & Uses'!C15 -> 482 | N40: =L40+M40 -> 482
B41: Total non-current liabilities | C41: =SUM(C33:C40) -> 286 | D41: =SUM(D33:D40) -> 304 | E41: =SUM(E33:E40) -> 5286.46 | F41: =SUM(F33:F40) -> 5511.6576 | G41: =SUM(G33:G40) -> 5830.5363 | H41: =SUM(H33:H40) -> 6093.8346 | I41: =SUM(I33:I40) -> 6314.6723 | J41: =SUM(J33:J40) -> 6466.5015 | L41: =SUM(L33:L40) -> 341 | M41: =SUM(M33:M40) -> 4945.46 | N41: =SUM(N33:N40) -> 5286.46
B43: Total liabilities | C43: =SUM(C41,C31) -> 370 | D43: =SUM(D41,D31) -> 413 | E43: =SUM(E41,E31) -> 5419.46 | F43: =SUM(F41,F31) -> 5668.9198 | G43: =SUM(G41,G31) -> 6016.4919 | H43: =SUM(H41,H31) -> 6310.8492 | I43: =SUM(I41,I31) -> 6565.1353 | J43: =SUM(J41,J31) -> 6753.4248 | L43: =SUM(L41,L31) -> 474 | M43: =SUM(M41,M31) -> 4945.46 | N43: =SUM(N41,N31) -> 5419.46
B45: Preferred stock | C45: 662 | D45: 0 | E45: 0 | F45: 0 | G45: 0 | H45: 0 | I45: 0 | J45: 0 | L45: 0 | M45: 0 | N45: 0
B46: Shareholder's equity | C46: -449 | D46: 570 | E46: =N46 -> 1516.6645 | F46: =E46+'Financial Statements'!F117 -> 1221.049 | G46: =F46+'Financial Statements'!G117 -> 976.45482 | H46: =G46+'Financial Statements'!H117 -> 792.76622 | I46: =H46+'Financial Statements'!I117 -> 678.40383 | J46: =I46+'Financial Statements'!J117 -> 642.13931 | L46: 696 | M46: =-L46+'Sources & Uses'!C16+'Sources & Uses'!C17 -> 820.66446 | N46: =L46+M46 -> 1516.6645
B48: Liabilites & shareholder's equity | C48: =C46+C43+C45 -> 583 | D48: =D46+D43+D45 -> 983 | E48: =E46+E43+E45 -> 6936.1244 | F48: =F46+F43+F45 -> 6889.9688 | G48: =G46+G43+G45 -> 6992.9467 | H48: =H46+H43+H45 -> 7103.6155 | I48: =I46+I43+I45 -> 7243.5391 | J48: =J46+J43+J45 -> 7395.5641 | L48: =L46+L43+L45 -> 1170 | N48: =N46+N43+N45 -> 6936.1244
B49: check | C49: =C48-C25 -> 0 | D49: =D48-D25 -> 0 | E49: =E48-E25 -> 0 | F49: =F48-F25 -> 0 | G49: =G48-G25 -> 0 | H49: =H48-H25 -> 0 | I49: =I48-I25 -> 0 | J49: =J48-J25 -> 0 | L49: =L48-L25 -> 0 | N49: =N48-N25 -> 0
B51: Statement of Cash Flows
B53: Net income | F53: ='Financial Statements'!F117 -> -295.61545 | G53: ='Financial Statements'!G117 -> -244.59419 | H53: ='Financial Statements'!H117 -> -183.6886 | I53: ='Financial Statements'!I117 -> -114.36239 | J53: ='Financial Statements'!J117 -> -36.264523
B54: Depreciation and amortization | F54: =-Schedules!F99 -> 211.09111 | G54: =-Schedules!G99 -> 207.01132 | H54: =-Schedules!H99 -> 208.5196 | I54: =-Schedules!I99 -> 212.29845 | J54: =-Schedules!J99 -> 218.00728
B55: PIK interest | F55: =Schedules!F199 -> 9.64 | G55: =Schedules!G199 -> 9.8328 | H55: =Schedules!H199 -> 10.029456 | I55: =Schedules!I199 -> 10.230045 | J55: =Schedules!J199 -> 10.434646
B56: Changes in accounts payable | F56: ='Financial Statements'!F28-'Financial Statements'!E28 -> 5.5671603 | G56: ='Financial Statements'!G28-'Financial Statements'!F28 -> 6.9784991 | H56: ='Financial Statements'!H28-'Financial Statements'!G28 -> 7.394294 | I56: ='Financial Statements'!I28-'Financial Statements'!H28 -> 7.6931514 | J56: ='Financial Statements'!J28-'Financial Statements'!I28 -> 8.464792
B57: Changes in accrued expenses | F57: ='Financial Statements'!F29-'Financial Statements'!E29 -> 18.694959 | G57: ='Financial Statements'!G29-'Financial Statements'!F29 -> 21.714973 | H57: ='Financial Statements'!H29-'Financial Statements'!G29 -> 23.664733 | I57: ='Financial Statements'!I29-'Financial Statements'!H29 -> 25.755181 | J57: ='Financial Statements'!J29-'Financial Statements'!I29 -> 27.995513
B58: Changes in inventories | F58: =-('Financial Statements'!F12-'Financial Statements'!E12) -> -1.7129724 | G58: =-('Financial Statements'!G12-'Financial Statements'!F12) -> -2.1472305 | H58: =-('Financial Statements'!H12-'Financial Statements'!G12) -> -2.2751674 | I58: =-('Financial Statements'!I12-'Financial Statements'!H12) -> -2.3671235 | J58: =-('Financial Statements'!J12-'Financial Statements'!I12) -> -2.6045514
B59: Changes in accounts receivable | F59: =-('Financial Statements'!F11-'Financial Statements'!E11) -> -3.5170495 | G59: =-('Financial Statements'!G11-'Financial Statements'!F11) -> -4.0438294 | H59: =-('Financial Statements'!H11-'Financial Statements'!G11) -> -4.4069197 | I59: =-('Financial Statements'!I11-'Financial Statements'!H11) -> -4.714887 | J59: =-('Financial Statements'!J11-'Financial Statements'!I11) -> -5.2947333
B60: Noncash deferred tax benefit | F60: =-'Tax Schedules '!F22 -> -107.05689 | G60: =-'Tax Schedules '!G22 -> -92.515654 | H60: =-'Tax Schedules '!H22 -> -84.578377 | I60: =-'Tax Schedules '!I22 -> -100.56674 | J60: =-'Tax Schedules '!J22 -> -100.91417
B61: Cash flows from operations | F61: =SUM(F53:F60) -> -162.90913 | G61: =SUM(G53:G60) -> -97.76331 | H61: =SUM(H53:H60) -> -25.34098 | I61: =SUM(I53:I60) -> 33.96568 | J61: =SUM(J53:J60) -> 119.82426
B63: Capex | F63: =-Schedules!F72 -> -178.10851 | G63: =-Schedules!G72 -> -211.28251 | H63: =-Schedules!H72 -> -227.92793 | I63: =-Schedules!I72 -> -244.57335 | J63: =-Schedules!J72 -> -261.21877
B64: Cash flows from investing | F64: =SUM(F63) -> -178.10851 | G64: =SUM(G63) -> -211.28251 | H64: =SUM(H63) -> -227.92793 | I64: =SUM(I63) -> -244.57335 | J64: =SUM(J63) -> -261.21877
B66: Free cash flow | F66: =F64+F61 -> -341.01764 | G66: =G64+G61 -> -309.04582 | H66: =H64+H61 -> -253.26891 | I66: =I64+I61 -> -210.60767 | J66: =J64+J61 -> -141.39451
B68: Borrowings (repayments) - revolver | F68: =SUM(Schedules!F133:F134) -> 482 | G68: =SUM(Schedules!G133:G134) -> 0 | H68: =SUM(Schedules!H133:H134) -> 0 | I68: =SUM(Schedules!I133:I134) -> 0 | J68: =SUM(Schedules!J133:J134) -> 0
B69: Borrowings (repayments) - TLA | F69: =SUM(Schedules!F153:F154) -> 90.377644 | G69: =SUM(Schedules!G153:G154) -> 0 | H69: =SUM(Schedules!H153:H154) -> 0 | I69: =SUM(Schedules!I153:I154) -> 0 | J69: =SUM(Schedules!J153:J154) -> 0
B70: Borrowings (repayments) - TLB | F70: =SUM(Schedules!F168:F169) -> 0 | G70: =SUM(Schedules!G168:G169) -> 539.63462 | H70: =SUM(Schedules!H168:H169) -> 493.89463 | I70: =SUM(Schedules!I168:I169) -> 54.645275 | J70: =SUM(Schedules!J168:J169) -> 56.747095
B71: Borrowings (repayments) - high yield | F71: =SUM(Schedules!F183:F184) -> 0 | G71: =SUM(Schedules!G183:G184) -> 0 | H71: =SUM(Schedules!H183:H184) -> 0 | I71: =SUM(Schedules!I183:I184) -> 405.50949 | J71: =SUM(Schedules!J183:J184) -> 76.49051
B72: Borrowings (repayments) - mezz | F72: =SUM(Schedules!F197:F198) -> 0 | G72: =SUM(Schedules!G197:G198) -> 0 | H72: =SUM(Schedules!H197:H198) -> 0 | I72: =SUM(Schedules!I197:I198) -> 0 | J72: =SUM(Schedules!J197:J198) -> 257.66196
B73: Mandatory amortization - TLA | F73: =Schedules!F155 -> -192.8 | G73: =Schedules!G155 -> -192.8 | H73: =Schedules!H155 -> -192.8 | I73: =Schedules!I155 -> -192.8 | J73: =Schedules!J155 -> -192.8
B74: Mandatory amortization - TLB | F74: =Schedules!F170 -> -38.56 | G74: =Schedules!G170 -> -37.7888 | H74: =Schedules!H170 -> -47.825716 | I74: =Schedules!I170 -> -56.747095 | J74: =Schedules!J170 -> -56.705058
B75: Cash flows from financing | F75: =SUM(F68:F74) -> 341.01764 | G75: =SUM(G68:G74) -> 309.04582 | H75: =SUM(H68:H74) -> 253.26891 | I75: =SUM(I68:I74) -> 210.60767 | J75: =SUM(J68:J74) -> 141.39451
B77: Change in cash | F77: =SUM(F75,F64,F61) -> 0 | G77: =SUM(G75,G64,G61) -> 0 | H77: =SUM(H75,H64,H61) -> 0 | I77: =SUM(I75,I64,I61) -> 0 | J77: =SUM(J75,J64,J61) -> 0
B79: Beginning cash | F79: ='Financial Statements'!N10 -> 100 | G79: =F80 -> 100 | H79: =G80 -> 100 | I79: =H80 -> 100 | J79: =I80 -> 100
B80: Ending cash | F80: =F79+F77 -> 100 | G80: =G79+G77 -> 100 | H80: =H79+H77 -> 100 | I80: =I79+I77 -> 100 | J80: =J79+J77 -> 100
B82: Income Statement
B84: Revenue | C84: 564 | D84: 729 | E84: 964 | F84: =Schedules!F31 -> 1221.4563 | G84: =Schedules!G31 -> 1520.5025 | H84: =Schedules!H31 -> 1846.3997 | I84: =Schedules!I31 -> 2201.0853 | J84: =Schedules!J31 -> 2586.6235
B85: COGS:
B86: Food, beverage, and packaging | C86: =-Schedules!C39 -> -180 | D86: =-Schedules!D39 -> -213 | E86: =-Schedules!E39 -> -285 | F86: =-Schedules!F39 -> -369.27602 | G86: =-Schedules!G39 -> -459.68498 | H86: =-Schedules!H39 -> -558.21165 | I86: =-Schedules!I39 -> -665.44176 | J86: =-Schedules!J39 -> -781.99936
B87: Labor | C87: =-Schedules!C40 -> -158 | D87: =-Schedules!D40 -> -187 | E87: =-Schedules!E40 -> -247 | F87: =-Schedules!F40 -> -267.45406 | G87: =-Schedules!G40 -> -317.08018 | H87: =-Schedules!H40 -> -366.70631 | I87: =-Schedules!I40 -> -416.33243 | J87: =-Schedules!J40 -> -465.95855
B88: Occupancy | C88: =-Schedules!C41 -> -54 | D88: =-Schedules!D41 -> -58 | E88: =-Schedules!E41 -> -70 | F88: =-Schedules!F41 -> -82.93802 | G88: =-Schedules!G41 -> -98.327177 | H88: =-Schedules!H41 -> -113.71633 | I88: =-Schedules!I41 -> -129.10549 | J88: =-Schedules!J41 -> -144.49465
B89: Other operating expenses | C89: =-Schedules!C42 -> -75 | D89: =-Schedules!D42 -> -89 | E89: =-Schedules!E42 -> -120 | F89: =-Schedules!F42 -> -154.53258 | G89: =-Schedules!G42 -> -192.36642 | H89: =-Schedules!H42 -> -233.59731 | I89: =-Schedules!I42 -> -278.47038 | J89: =-Schedules!J42 -> -327.24676
B90: COGS | C90: -466 | D90: -548 | E90: -722 | F90: =-Schedules!F43 -> -874.20069 | G90: =-Schedules!G43 -> -1067.4588 | H90: =-Schedules!H43 -> -1272.2316 | I90: =-Schedules!I43 -> -1489.3501 | J90: =-Schedules!J43 -> -1719.6993
B92: Gross income | C92: =SUM(C90,C84) -> 98 | D92: =SUM(D90,D84) -> 181 | E92: =SUM(E90,E84) -> 242 | F92: =SUM(F90,F84) -> 347.25561 | G92: =SUM(G90,G84) -> 453.04372 | H92: =SUM(H90,H84) -> 574.16807 | I92: =SUM(I90,I84) -> 711.73524 | J92: =SUM(J90,J84) -> 866.92418
B94: SG&A:
B95: G&A | C95: =-Schedules!C45 -> -70 | D95: =-Schedules!D45 -> -101 | E95: =-Schedules!E45 -> -120 | F95: =-Schedules!F45 -> -141.0132 | G95: =-Schedules!G45 -> -158.27516 | H95: =-Schedules!H45 -> -175.23713 | I95: =-Schedules!I45 -> -192.06829 | J95: =-Schedules!J45 -> -208.88946
B96: Restructuring expenses | C96: =-Schedules!C46 -> -6 | D96: =-Schedules!D46 -> -6 | E96: =-Schedules!E46 -> -1 | F96: =-Schedules!F46 -> -7.3862069 | G96: =-Schedules!G46 -> -8.7672414 | H96: =-Schedules!H46 -> -8.7672414 | I96: =-Schedules!I46 -> -8.7672414 | J96: =-Schedules!J46 -> -8.7672414
B97: SG&A | C97: -76 | D97: -107 | E97: -121 | F97: =-Schedules!F47 -> -148.39941 | G97: =-Schedules!G47 -> -167.0424 | H97: =-Schedules!H47 -> -184.00437 | I97: =-Schedules!I47 -> -200.83553 | J97: =-Schedules!J47 -> -217.6567
B98: Pre-opening costs | C98: -19 | D98: -16 | E98: -12 | F98: =-Schedules!F49 -> -25.167816 | G98: =-Schedules!G49 -> -29.873563 | H98: =-Schedules!H49 -> -29.873563 | I98: =-Schedules!I49 -> -29.873563 | J98: =-Schedules!J49 -> -29.873563
B99: Impairment and asset disposal costs | C99: -20 | D99: -5 | E99: -5 | F99: =-Schedules!F50 -> 0 | G99: =-Schedules!G50 -> 0 | H99: =-Schedules!H50 -> 0 | I99: =-Schedules!I50 -> 0 | J99: =-Schedules!J50 -> 0
B101: EBITDA | C101: =SUM(C97,C92,C98:C99) -> -17 | D101: =SUM(D97,D92,D98:D99) -> 53 | E101: =SUM(E97,E92,E98:E99) -> 104 | F101: =SUM(F97,F92) -> 198.8562 | G101: =SUM(G97,G92) -> 286.00132 | H101: =SUM(H97,H92) -> 390.1637 | I101: =SUM(I97,I92) -> 510.89971 | J101: =SUM(J97,J92) -> 649.26748
B103: D&A:
B104: D&A - base PP&E | C104: =Schedules!C96 -> -43 | D104: =Schedules!D96 -> -48 | E104: =Schedules!E96 -> -61 | F104: =Schedules!F96 -> -145.56427 | G104: =Schedules!G96 -> -141.48448 | H104: =Schedules!H96 -> -142.99275 | I104: =Schedules!I96 -> -146.7716 | J104: =Schedules!J96 -> -152.48044
B105: D&A - incremental PP&E | C105: =Schedules!C97 -> 0 | D105: =Schedules!D97 -> 0 | E105: =Schedules!E97 -> 0 | F105: =Schedules!F97 -> -59.742844 | G105: =Schedules!G97 -> -59.742844 | H105: =Schedules!H97 -> -59.742844 | I105: =Schedules!I97 -> -59.742844 | J105: =Schedules!J97 -> -59.742844
B106: Financing fees | C106: =Schedules!C98 -> 0 | D106: =Schedules!D98 -> 0 | E106: =Schedules!E98 -> 0 | F106: =Schedules!F98 -> -5.784 | G106: =Schedules!G98 -> -5.784 | H106: =Schedules!H98 -> -5.784 | I106: =Schedules!I98 -> -5.784 | J106: =Schedules!J98 -> -5.784
B107: Depreciation and amortization | C107: -43 | D107: -48 | E107: -61 | F107: =Schedules!F99 -> -211.09111 | G107: =Schedules!G99 -> -207.01132 | H107: =Schedules!H99 -> -208.5196 | I107: =Schedules!I99 -> -212.29845 | J107: =Schedules!J99 -> -218.00728
B109: EBIT | C109: =SUM(C107,C101) -> -60 | D109: =SUM(D107,D101) -> 5 | E109: =SUM(E107,E101) -> 43 | F109: =SUM(F107,F101) -> -12.234913 | G109: =SUM(G107,G101) -> 78.990001 | H109: =SUM(H107,H101) -> 181.6441 | I109: =SUM(I107,I101) -> 298.60126 | J109: =SUM(J107,J101) -> 431.2602
B111: Interest (expense) income | C111: 1 | D111: 9 | E111: 17 | F111: =-'Ratios & Statistics'!F28 -> -389.4544 | G111: =-'Ratios & Statistics'!G28 -> -411.35041 | H111: =-'Ratios & Statistics'!H28 -> -431.24454 | I111: =-'Ratios & Statistics'!I28 -> -453.9996 | J111: =-'Ratios & Statistics'!J28 -> -480.5373
B113: EBT | C113: =SUM(C111,C109) -> -59 | D113: =SUM(D111,D109) -> 14 | E113: =SUM(E111,E109) -> 60 | F113: =SUM(F111,F109) -> -401.68931 | G113: =SUM(G111,G109) -> -332.36041 | H113: =SUM(H111,H109) -> -249.60044 | I113: =SUM(I111,I109) -> -155.39834 | J113: =SUM(J111,J109) -> -49.277097
B115: Income tax (expense) benefit | C115: 0 | D115: -1 | E115: 70 | F115: =-'Tax Schedules '!F56 -> 106.07386 | G115: =-'Tax Schedules '!G56 -> 87.766217 | H115: =-'Tax Schedules '!H56 -> 65.911841 | I115: =-'Tax Schedules '!I56 -> 41.035948 | J115: =-'Tax Schedules '!J56 -> 13.012574 | L115: * using accural accounting for NOL generation, reconciled with DTA generation
B117: Net income | C117: =SUM(C115,C113) -> -59 | D117: =SUM(D115,D113) -> 13 | E117: =SUM(E115,E113) -> 130 | F117: =SUM(F115,F113) -> -295.61545 | G117: =SUM(G115,G113) -> -244.59419 | H117: =SUM(H115,H113) -> -183.6886 | I117: =SUM(I115,I113) -> -114.36239 | J117: =SUM(J115,J113) -> -36.264523

Sheet Schedules
C2: Most Recent 10k | L2: IRR | M2: ='Exit Waterfall'!C43 -> 0.1957715
B3: $ millions | L3: MoIC | M3: ='Exit Waterfall'!C44 -> 2.4447868
C4: 2022 | D4: 2023 | E4: 2024 | F4: 2025 | G4: 2026 | H4: 2027 | I4: 2028 | J4: 2029
B6: Excess Purchase Price Accounting
B8: Adjustments to assets | C8: ='Financial Statements'!M10+'Financial Statements'!M22 -> -208.16
B9: Adjustments to liabilities & SE | C9: =SUM('Financial Statements'!M33:M40,'Financial Statements'!M46) -> 5766.1244
B10: Excess purchase price | C10: =C9-C8 -> 5974.2844
B12: Goodwill allocation | C12: =C10*Assumptions!C49 -> 5376.856
B13: PP&E allocation | C13: =C10*Assumptions!C50 -> 597.42844
B15: Deferred tax liability | C15: =C13*Assumptions!C27 -> 125.45997
B16: Annual DTL unwind | C16: =C15/Assumptions!C51 -> 12.545997
B18: Revenue Growth Schedule
B20: Total number of locations | C20: 279 | D20: 309 | E20: 367 | F20: =F21+E20 -> 435 | G20: =($M$20-$F$20)/7+F20 -> 515.71429 | H20: =($M$20-$F$20)/7+G20 -> 596.42857 | I20: =($M$20-$F$20)/7+H20 -> 677.14286 | J20: =($M$20-$F$20)/7+I20 -> 757.85714 | K20: =($M$20-$F$20)/7+J20 -> 838.57143 | L20: =($M$20-$F$20)/7+K20 -> 919.28571 | M20: 1000
B21: Number of new locations (∆loc) | D21: =D20-C20 -> 30 | E21: =E20-D20 -> 58 | F21: 68 | G21: =G20-F20 -> 80.714286 | H21: =H20-G20 -> 80.714286 | I21: =I20-H20 -> 80.714286 | J21: =J20-I20 -> 80.714286 | K21: =K20-J20 -> 80.714286 | L21: =L20-K20 -> 80.714286 | M21: =M20-L20 -> 80.714286 | O21: management quotes 1000 restaurants by 2032, I assume a flat rate of openings till then
B23: Growth in # of stores - % | D23: =D21/C20 -> 0.10752688 | E23: =E21/D20 -> 0.18770227 | F23: =F21/E20 -> 0.1852861 | G23: =G21/F20 -> 0.18555008 | H23: =H21/G20 -> 0.1565097 | I23: =I21/H20 -> 0.13532934 | J23: =J21/I20 -> 0.11919831 | O23: recent customer traffic "approximately flat"
B25: Same store volume growth | F25: 0.01 | G25: 0.02 | H25: =$G$25 -> 0.02 | I25: =$G$25 -> 0.02 | J25: =$G$25 -> 0.02 | O25: 5-year consumer inflation expectation assumed to hold for food inflation
B26: PMO growth | F26: 0.059 | G26: 0.03 | H26: =$G$26 -> 0.03 | I26: =$G$26 -> 0.03 | J26: =$G$26 -> 0.03 | O26: one-year ahead food inflation expectation 5.9%
B28: Same store sales growth - % | F28: =SUM(F25:F26) -> 0.069 | G28: =SUM(G25:G26) -> 0.05 | H28: =SUM(H25:H26) -> 0.05 | I28: =SUM(I25:I26) -> 0.05 | J28: =SUM(J25:J26) -> 0.05 | O28: management guides 6-8% same-store sales growth in 2025
B29: Same store sales - $thousands | C29: =C31/C20*1000 -> 2021.5054 | D29: =D31/D20*1000 -> 2359.2233 | E29: =E31/E20*1000 -> 2626.703 | F29: =E29*(1+F28) -> 2807.9455 | G29: =F29*(1+G28) -> 2948.3428 | H29: =G29*(1+H28) -> 3095.7599 | I29: =H29*(1+I28) -> 3250.5479 | J29: =I29*(1+J28) -> 3413.0753
B31: Revenue | C31: ='Financial Statements'!C84 -> 564 | D31: ='Financial Statements'!D84 -> 729 | E31: ='Financial Statements'!E84 -> 964 | F31: =F29*F20/1000 -> 1221.4563 | G31: =G29*G20/1000 -> 1520.5025 | H31: =H29*H20/1000 -> 1846.3997 | I31: =I29*I20/1000 -> 2201.0853 | J31: =J29*J20/1000 -> 2586.6235
B33: Operating Expenses Schedules
B35: Revenue | C35: ='Financial Statements'!C84 -> 564 | D35: ='Financial Statements'!D84 -> 729 | E35: ='Financial Statements'!E84 -> 964 | F35: ='Financial Statements'!F84 -> 1221.4563 | G35: ='Financial Statements'!G84 -> 1520.5025 | H35: ='Financial Statements'!H84 -> 1846.3997 | I35: ='Financial Statements'!I84 -> 2201.0853 | J35: ='Financial Statements'!J84 -> 2586.6235
B36: Number of stores | C36: =C20 -> 279 | D36: =D20 -> 309 | E36: =E20 -> 367 | F36: =F20 -> 435 | G36: =G20 -> 515.71429 | H36: =H20 -> 596.42857 | I36: =I20 -> 677.14286 | J36: =J20 -> 757.85714
B37: Number of net new locations | C37: =C21 -> 0 | D37: =D21 -> 30 | E37: =E21 -> 58 | F37: =F21 -> 68 | G37: =G21 -> 80.714286 | H37: =H21 -> 80.714286 | I37: =I21 -> 80.714286 | J37: =J21 -> 80.714286
B39: Food, beverage, and packaging | C39: 180 | D39: 213 | E39: 285 | F39: =F52*F35 -> 369.27602 | G39: =G52*G35 -> 459.68498 | H39: =H52*H35 -> 558.21165 | I39: =I52*I35 -> 665.44176 | J39: =J52*J35 -> 781.99936 | L39: * assumption for operating cost components is that their prices inflate at the same rate at revenue, 5.9% in future Y1 and 3.0% thereafter
B40: Labor | C40: 158 | D40: 187 | E40: 247 | F40: =F53*F36 -> 267.45406 | G40: =G53*G36 -> 317.08018 | H40: =H53*H36 -> 366.70631 | I40: =I53*I36 -> 416.33243 | J40: =J53*J36 -> 465.95855
B41: Occupancy | C41: 54 | D41: 58 | E41: 70 | F41: =F54*F36 -> 82.93802 | G41: =G54*G36 -> 98.327177 | H41: =H54*H36 -> 113.71633 | I41: =I54*I36 -> 129.10549 | J41: =J54*J36 -> 144.49465
B42: Other operating expenses | C42: 75 | D42: 89 | E42: 120 | F42: =F55*F35 -> 154.53258 | G42: =G55*G35 -> 192.36642 | H42: =H55*H35 -> 233.59731 | I42: =I55*I35 -> 278.47038 | J42: =J55*J35 -> 327.24676
B43: COGS | C43: =SUM(C39:C42) -> 467 | D43: =SUM(D39:D42) -> 547 | E43: =SUM(E39:E42) -> 722 | F43: =SUM(F39:F42) -> 874.20069 | G43: =SUM(G39:G42) -> 1067.4588 | H43: =SUM(H39:H42) -> 1272.2316 | I43: =SUM(I39:I42) -> 1489.3501 | J43: =SUM(J39:J42) -> 1719.6993
B45: G&A | C45: 70 | D45: 101 | E45: 120 | F45: =AVERAGE(C56:E56)*AVERAGE(F35,E35) -> 141.0132 | G45: =AVERAGE(F56)*AVERAGE(G35,F35) -> 158.27516 | H45: =AVERAGE(G56)*AVERAGE(H35,G35) -> 175.23713 | I45: =AVERAGE(H56)*AVERAGE(I35,H35) -> 192.06829 | J45: =AVERAGE(I56)*AVERAGE(J35,I35) -> 208.88946 | L45: * does not break down G&A, but I expect economies of scale will increase G&A at half the rate of revenue
B46: Restructuring expenses | C46: 6 | D46: 6 | E46: 1 | F46: =F57*F37 -> 7.3862069 | G46: =G57*G37 -> 8.7672414 | H46: =H57*H37 -> 8.7672414 | I46: =I57*I37 -> 8.7672414 | J46: =J57*J37 -> 8.7672414
B47: SG&A | C47: =SUM(C45:C46) -> 76 | D47: =SUM(D45:D46) -> 107 | E47: =SUM(E45:E46) -> 121 | F47: =SUM(F45:F46) -> 148.39941 | G47: =SUM(G45:G46) -> 167.0424 | H47: =SUM(H45:H46) -> 184.00437 | I47: =SUM(I45:I46) -> 200.83553 | J47: =SUM(J45:J46) -> 217.6567
B49: Pre-opening costs | C49: =-'Financial Statements'!C98 -> 19 | D49: =-'Financial Statements'!D98 -> 16 | E49: =-'Financial Statements'!E98 -> 12 | F49: =F58*F37 -> 25.167816 | G49: =G58*G37 -> 29.873563 | H49: =H58*H37 -> 29.873563 | I49: =I58*I37 -> 29.873563 | J49: =J58*J37 -> 29.873563
B50: Impairment and asset disposal | C50: =-'Financial Statements'!C99 -> 20 | D50: =-'Financial Statements'!D99 -> 5 | E50: =-'Financial Statements'!E99 -> 5 | F50: 0 | G50: 0 | H50: 0 | I50: 0 | J50: 0 | L50: expecting 0 net impairment after precedent
B52: Food & beverage - % of revenue | C52: =C39/C35 -> 0.31914894 | D52: =D39/D35 -> 0.29218107 | E52: =E39/E35 -> 0.29564315 | F52: =AVERAGE(C52:E52) -> 0.30232439 | G52: =$F52 -> 0.30232439 | H52: =$F52 -> 0.30232439 | I52: =$F52 -> 0.30232439 | J52: =$F52 -> 0.30232439
B53: Labor - % of stores | C53: =C40/C36 -> 0.56630824 | D53: =D40/D36 -> 0.60517799 | E53: =E40/E36 -> 0.67302452 | F53: =AVERAGE(C53:E53) -> 0.61483692 | G53: =$F53 -> 0.61483692 | H53: =$F53 -> 0.61483692 | I53: =$F53 -> 0.61483692 | J53: =$F53 -> 0.61483692
B54: Occupancy - % of stores | C54: =C41/C36 -> 0.19354839 | D54: =D41/D36 -> 0.18770227 | E54: =E41/E36 -> 0.19073569 | F54: =AVERAGE(C54:E54) -> 0.19066212 | G54: =$F54 -> 0.19066212 | H54: =$F54 -> 0.19066212 | I54: =$F54 -> 0.19066212 | J54: =$F54 -> 0.19066212
B55: Other operating expense - % of revenue | C55: =C42/C35 -> 0.13297872 | D55: =D42/D35 -> 0.12208505 | E55: =E42/E35 -> 0.12448133 | F55: =AVERAGE(C55:E55) -> 0.12651503 | G55: =$F55 -> 0.12651503 | H55: =$F55 -> 0.12651503 | I55: =$F55 -> 0.12651503 | J55: =$F55 -> 0.12651503
B56: G&A - % of revenue | C56: =C45/C35 -> 0.12411348 | D56: =D45/D35 -> 0.13854595 | E56: =E45/E35 -> 0.12448133 | F56: =F45/F35 -> 0.11544678 | G56: =G45/G35 -> 0.10409398 | H56: =H45/H35 -> 0.094907474 | I56: =I45/I35 -> 0.08726072 | J56: =J45/J35 -> 0.080757581
B57: Restructuring expenses - % of new stores | D57: =D46/D37 -> 0.2 | E57: =E46/E37 -> 0.017241379 | F57: =AVERAGE(C57:E57) -> 0.10862069 | G57: =$F57 -> 0.10862069 | H57: =$F57 -> 0.10862069 | I57: =$F57 -> 0.10862069 | J57: =$F57 -> 0.10862069
B58: Pre-opening costs - % of new stores | D58: =D49/D37 -> 0.53333333 | E58: =E49/E37 -> 0.20689655 | F58: =AVERAGE(C58:E58) -> 0.37011494 | G58: =$F58 -> 0.37011494 | H58: =$F58 -> 0.37011494 | I58: =$F58 -> 0.37011494 | J58: =$F58 -> 0.37011494
B59: Impairment and asset disposal - % of revenue | C59: =C50/C35 -> 0.035460993 | D59: =D50/D35 -> 0.0068587106 | E59: =E50/E35 -> 0.005186722 | F59: =F50/F35 -> 0 | G59: =G50/G35 -> 0 | H59: =H50/H35 -> 0 | I59: =I50/I35 -> 0 | J59: =J50/J35 -> 0
B61: Capex Schedule
B63: Expected capex from each new restaurant (m) | C63: 1.3 | L63: CAVA states expectation of $1.3m in capex for each new restaurant opening
B65: Number of new restaurants | D65: =D37 -> 30 | E65: =E37 -> 58 | F65: =F37 -> 68 | G65: =G37 -> 80.714286 | H65: =H37 -> 80.714286 | I65: =I37 -> 80.714286 | J65: =J37 -> 80.714286
B66: Expected capex from openings | D66: =D65*1.3 -> 39 | E66: =E65*1.3 -> 75.4 | F66: =F65*1.3 -> 88.4 | G66: =G65*1.3 -> 104.92857 | H66: =H65*1.3 -> 104.92857 | I66: =I65*1.3 -> 104.92857 | J66: =J65*1.3 -> 104.92857
B68: Remaining capex | D68: =D72-D66 -> 100 | E68: =E72-E66 -> 32.6 | F68: =F69*F70 -> 89.708513 | G68: =G69*G70 -> 106.35393 | H68: =H69*H70 -> 122.99936 | I68: =I69*I70 -> 139.64478 | J68: =J69*J70 -> 156.2902
B69: Number of stores | C69: =C36 -> 279 | D69: =D36 -> 309 | E69: =E36 -> 367 | F69: =F36 -> 435 | G69: =G36 -> 515.71429 | H69: =H36 -> 596.42857 | I69: =I36 -> 677.14286 | J69: =J36 -> 757.85714
B70: Capex per existing store | D70: =D68/D69 -> 0.3236246 | E70: =E68/E69 -> 0.088828338 | F70: =AVERAGE(D70:E70) -> 0.20622647 | G70: =$F$70 -> 0.20622647 | H70: =$F$70 -> 0.20622647 | I70: =$F$70 -> 0.20622647 | J70: =$F$70 -> 0.20622647
B72: Total capex | C72: 104 | D72: 139 | E72: 108 | F72: =F68+F66 -> 178.10851 | G72: =G68+G66 -> 211.28251 | H72: =H68+H66 -> 227.92793 | I72: =I68+I66 -> 244.57335 | J72: =J68+J66 -> 261.21877
B74: Net Working Capital Schedule
B76: Accounts receivable | C76: ='Financial Statements'!C11 -> 8 | D76: ='Financial Statements'!D11 -> 12 | E76: ='Financial Statements'!E11 -> 13 | F76: =F89/F87*F84 -> 16.51705 | G76: =G89/G87*G84 -> 20.560879 | H76: =H89/H87*H84 -> 24.967799 | I76: =I89/I87*I84 -> 29.682686 | J76: =J89/J87*J84 -> 34.977419
B77: Inventories | C77: ='Financial Statements'!C12 -> 5 | D77: ='Financial Statements'!D12 -> 6 | E77: ='Financial Statements'!E12 -> 8 | F77: =F90/F87*F85 -> 9.7129724 | G77: =G90/G87*G85 -> 11.860203 | H77: =H90/H87*H85 -> 14.13537 | I77: =I90/I87*I85 -> 16.502494 | J77: =J90/J87*J85 -> 19.107045
B78: Current changeable assets | C78: =SUM(C76:C77) -> 13 | D78: =SUM(D76:D77) -> 18 | E78: =SUM(E76:E77) -> 21 | F78: =SUM(F76:F77) -> 26.230022 | G78: =SUM(G76:G77) -> 32.421082 | H78: =SUM(H76:H77) -> 39.103169 | I78: =SUM(I76:I77) -> 46.185179 | J78: =SUM(J76:J77) -> 54.084464
B80: Accounts payable | C80: ='Financial Statements'!C28 -> 14 | D80: ='Financial Statements'!D28 -> 17 | E80: ='Financial Statements'!E28 -> 26 | F80: =F91/F87*F85 -> 31.56716 | G80: =G91/G87*G85 -> 38.545659 | H80: =H91/H87*H85 -> 45.939953 | I80: =I91/I87*I85 -> 53.633105 | J80: =J91/J87*J85 -> 62.097897
B81: Accrued expenses | C81: ='Financial Statements'!C29 -> 40 | D81: ='Financial Statements'!D29 -> 59 | E81: ='Financial Statements'!E29 -> 70 | F81: =F92*F84 -> 88.694959 | G81: =G92*G84 -> 110.40993 | H81: =H92*H84 -> 134.07466 | I81: =I92*I84 -> 159.82985 | J81: =J92*J84 -> 187.82536
B82: Current changeable liabilities | C82: =SUM(C80:C81) -> 54 | D82: =SUM(D80:D81) -> 76 | E82: =SUM(E80:E81) -> 96 | F82: =SUM(F80:F81) -> 120.26212 | G82: =SUM(G80:G81) -> 148.95559 | H82: =SUM(H80:H81) -> 180.01462 | I82: =SUM(I80:I81) -> 213.46295 | J82: =SUM(J80:J81) -> 249.92325
B84: Revenue | C84: ='Financial Statements'!C84 -> 564 | D84: ='Financial Statements'!D84 -> 729 | E84: ='Financial Statements'!E84 -> 964 | F84: ='Financial Statements'!F84 -> 1221.4563 | G84: ='Financial Statements'!G84 -> 1520.5025 | H84: ='Financial Statements'!H84 -> 1846.3997 | I84: ='Financial Statements'!I84 -> 2201.0853 | J84: ='Financial Statements'!J84 -> 2586.6235
B85: COGS | C85: =-'Financial Statements'!C90 -> 466 | D85: =-'Financial Statements'!D90 -> 548 | E85: =-'Financial Statements'!E90 -> 722 | F85: =-'Financial Statements'!F90 -> 874.20069 | G85: =-'Financial Statements'!G90 -> 1067.4588 | H85: =-'Financial Statements'!H90 -> 1272.2316 | I85: =-'Financial Statements'!I90 -> 1489.3501 | J85: =-'Financial Statements'!J90 -> 1719.6993
B87: Days | C87: 365 | D87: 365 | E87: 366 | F87: 365 | G87: 365 | H87: 365 | I87: 366 | J87: 365
B89: Days receivables outstanding | C89: =C76/C84*C87 -> 5.177305 | D89: =D76/D84*D87 -> 6.0082305 | E89: =E76/E84*E87 -> 4.9356846 | F89: =$E$89 -> 4.9356846 | G89: =$E$89 -> 4.9356846 | H89: =$E$89 -> 4.9356846 | I89: =$E$89 -> 4.9356846 | J89: =$E$89 -> 4.9356846
B90: Days inventory outstanding | C90: =C77/C85*C87 -> 3.916309 | D90: =D77/D85*D87 -> 3.9963504 | E90: =E77/E85*E87 -> 4.0554017 | F90: =$E$90 -> 4.0554017 | G90: =$E$90 -> 4.0554017 | H90: =$E$90 -> 4.0554017 | I90: =$E$90 -> 4.0554017 | J90: =$E$90 -> 4.0554017
B91: Days payable outstanding | C91: =C80/C85*C87 -> 10.965665 | D91: =D80/D85*D87 -> 11.322993 | E91: =E80/E85*E87 -> 13.180055 | F91: =$E$91 -> 13.180055 | G91: =$E$91 -> 13.180055 | H91: =$E$91 -> 13.180055 | I91: =$E$91 -> 13.180055 | J91: =$E$91 -> 13.180055
B92: Accrued expenses - % of revenue | C92: =C81/C84 -> 0.070921986 | D92: =D81/D84 -> 0.080932785 | E92: =E81/E84 -> 0.072614108 | F92: =$E$92 -> 0.072614108 | G92: =$E$92 -> 0.072614108 | H92: =$E$92 -> 0.072614108 | I92: =$E$92 -> 0.072614108 | J92: =$E$92 -> 0.072614108
B94: D&A Schedule
B96: D&A - base PP&E | C96: ='Financial Statements'!C107 -> -43 | D96: ='Financial Statements'!D107 -> -48 | E96: ='Financial Statements'!E107 -> -61 | F96: =-E101*F102 -> -145.56427 | G96: =-F101*G102 -> -141.48448 | H96: =-G101*H102 -> -142.99275 | I96: =-H101*I102 -> -146.7716 | J96: =-I101*J102 -> -152.48044
B97: D&A - incremental PP&E | C97: 0 | D97: 0 | E97: 0 | F97: =-$C$110 -> -59.742844 | G97: =-$C$110 -> -59.742844 | H97: =-$C$110 -> -59.742844 | I97: =-$C$110 -> -59.742844 | J97: =-$C$110 -> -59.742844
B98: Financing fees | C98: 0 | D98: 0 | E98: 0 | F98: =-$C$106 -> -5.784 | G98: =-$C$106 -> -5.784 | H98: =-$C$106 -> -5.784 | I98: =-$C$106 -> -5.784 | J98: =-$C$106 -> -5.784
B99: Total D&A | C99: =SUM(C96:C98) -> -43 | D99: =SUM(D96:D98) -> -48 | E99: =SUM(E96:E98) -> -61 | F99: =SUM(F96:F98) -> -211.09111 | G99: =SUM(G96:G98) -> -207.01132 | H99: =SUM(H96:H98) -> -208.5196 | I99: =SUM(I96:I98) -> -212.29845 | J99: =SUM(J96:J98) -> -218.00728
B101: PP&E | C101: ='Financial Statements'!C16 -> 243 | D101: ='Financial Statements'!D16 -> 331 | E101: ='Financial Statements'!E16 -> 970.42844 | F101: =F120 -> 943.22985 | G101: =G120 -> 953.28503 | H101: =H120 -> 978.47736 | I101: =I120 -> 1016.5363 | J101: =J120 -> 1065.5318
B102: D&A - base PP&E - % of PP&E | D102: =-D99/C101 -> 0.19753086 | E102: =-E99/D101 -> 0.18429003 | F102: 0.15 | G102: 0.15 | H102: 0.15 | I102: 0.15 | J102: 0.15
B104: Financing fees | C104: ='Financial Statements'!E22 -> 57.84
B105: Useful life | C105: =Assumptions!C43 -> 10
B106: D&A - financing fees | C106: =C104/C105 -> 5.784
B108: Incremental PP&E | C108: =C13 -> 597.42844
B109: Useful life | C109: =Assumptions!C51 -> 10
B110: D&A - incremental PP&E | C110: =C108/C109 -> 59.742844
B112: Financing fees | C112: 0 | D112: 0 | E112: =C104 -> 57.84 | F112: =E112-$C$106 -> 52.056 | G112: =F112-$C$106 -> 46.272 | H112: =G112-$C$106 -> 40.488 | I112: =H112-$C$106 -> 34.704 | J112: =I112-$C$106 -> 28.92
B114: PP&E Schedule
B116: PP&E beginning | F116: =E120 -> 970.42844 | G116: =F120 -> 943.22985 | H116: =G120 -> 953.28503 | I116: =H120 -> 978.47736 | J116: =I120 -> 1016.5363
B117: + Capex | F117: =F72 -> 178.10851 | G117: =G72 -> 211.28251 | H117: =H72 -> 227.92793 | I117: =I72 -> 244.57335 | J117: =J72 -> 261.21877
B118: - Base D&A | F118: =F96 -> -145.56427 | G118: =G96 -> -141.48448 | H118: =H96 -> -142.99275 | I118: =I96 -> -146.7716 | J118: =J96 -> -152.48044
B119: - Incremental D&A | F119: =F97 -> -59.742844 | G119: =G97 -> -59.742844 | H119: =H97 -> -59.742844 | I119: =I97 -> -59.742844 | J119: =J97 -> -59.742844
B120: PP&E ending | E120: ='Financial Statements'!E16 -> 970.42844 | F120: =SUM(F116:F119) -> 943.22985 | G120: =SUM(G116:G119) -> 953.28503 | H120: =SUM(H116:H119) -> 978.47736 | I120: =SUM(I116:I119) -> 1016.5363 | J120: =SUM(J116:J119) -> 1065.5318
B122: Debt Schedule
B124: Revolver
B126: Free cash flow | F126: ='Financial Statements'!F66 -> -341.01764 | G126: ='Financial Statements'!G66 -> -309.04582 | H126: ='Financial Statements'!H66 -> -253.26891 | I126: ='Financial Statements'!I66 -> -210.60767 | J126: ='Financial Statements'!J66 -> -141.39451
B127: Opening cash balance | F127: ='Financial Statements'!E10 -> 100 | G127: =F208 -> 100 | H127: =G208 -> 100 | I127: =H208 -> 100 | J127: =I208 -> 100
B128: Minimum cash balance | F128: =-Assumptions!$C$22 -> -100 | G128: =-Assumptions!$C$22 -> -100 | H128: =-Assumptions!$C$22 -> -100 | I128: =-Assumptions!$C$22 -> -100 | J128: =-Assumptions!$C$22 -> -100
B129: Mandatory amortization | F129: =F155+F170 -> -231.36 | G129: =G155+G170 -> -230.5888 | H129: =H155+H170 -> -240.62572 | I129: =I155+I170 -> -249.54709 | J129: =J155+J170 -> -249.50506
B130: Cash available for revolver | F130: =SUM(F126:F129) -> -572.37764 | G130: =SUM(G126:G129) -> -539.63462 | H130: =SUM(H126:H129) -> -493.89463 | I130: =SUM(I126:I129) -> -460.15476 | J130: =SUM(J126:J129) -> -390.89957
B132: Opening balance | F132: ='Financial Statements'!E36 -> 482 | G132: =F135 -> 964 | H132: =G135 -> 964 | I132: =H135 -> 964 | J132: =I135 -> 964
B133: Borrowings | F133: =IF(F130>=0,0,IF(F132-F130>Assumptions!$J$37,Assumptions!$J$37-F132,-F130)) -> 482 | G133: =IF(G130>=0,0,IF(G132-G130>Assumptions!$J$37,Assumptions!$J$37-G132,-G130)) -> 0 | H133: =IF(H130>=0,0,IF(H132-H130>Assumptions!$J$37,Assumptions!$J$37-H132,-H130)) -> 0 | I133: =IF(I130>=0,0,IF(I132-I130>Assumptions!$J$37,Assumptions!$J$37-I132,-I130)) -> 0 | J133: =IF(J130>=0,0,IF(J132-J130>Assumptions!$J$37,Assumptions!$J$37-J132,-J130)) -> 0
B134: Repayments | F134: =-IF(F133=0,IF(F130>F132,F132,IF(F130<0,0,F130)),0) -> 0 | G134: =-IF(G133=0,IF(G130>G132,G132,IF(G130<0,0,G130)),0) -> 0 | H134: =-IF(H133=0,IF(H130>H132,H132,IF(H130<0,0,H130)),0) -> 0 | I134: =-IF(I133=0,IF(I130>I132,I132,IF(I130<0,0,I130)),0) -> 0 | J134: =-IF(J133=0,IF(J130>J132,J132,IF(J130<0,0,J130)),0) -> 0
B135: Ending balance | F135: =SUM(F132:F134) -> 964 | G135: =SUM(G132:G134) -> 964 | H135: =SUM(H132:H134) -> 964 | I135: =SUM(I132:I134) -> 964 | J135: =SUM(J132:J134) -> 964
B137: Cash interest rate | F137: =Assumptions!$E$37 -> 0.0624 | G137: =Assumptions!$E$37 -> 0.0624 | H137: =Assumptions!$E$37 -> 0.0624 | I137: =Assumptions!$E$37 -> 0.0624 | J137: =Assumptions!$E$37 -> 0.0624
B138: Cash interest expense | F138: =IF(Assumptions!$C$45="Yes",F137*AVERAGE(F132,F135),F137*F132) -> 45.1152 | G138: =IF(Assumptions!$C$45="Yes",G137*AVERAGE(G132,G135),G137*G132) -> 60.1536 | H138: =IF(Assumptions!$C$45="Yes",H137*AVERAGE(H132,H135),H137*H132) -> 60.1536 | I138: =IF(Assumptions!$C$45="Yes",I137*AVERAGE(I132,I135),I137*I132) -> 60.1536 | J138: =IF(Assumptions!$C$45="Yes",J137*AVERAGE(J132,J135),J137*J132) -> 60.1536
B140: Revolver commitment | F140: =Assumptions!$J$37 -> 964 | G140: =Assumptions!$J$37 -> 964 | H140: =Assumptions!$J$37 -> 964 | I140: =Assumptions!$J$37 -> 964 | J140: =Assumptions!$J$37 -> 964
B141: Revolver unused commitment | F141: =IF(Assumptions!C45="Yes",F140-AVERAGE(F132,F135),F140-F132) -> 241 | G141: =IF(Assumptions!$C$45="Yes",G140-AVERAGE(G132,G135),G140-G132) -> 0 | H141: =IF(Assumptions!$C$45="Yes",H140-AVERAGE(H132,H135),H140-H132) -> 0 | I141: =IF(Assumptions!$C$45="Yes",I140-AVERAGE(I132,I135),I140-I132) -> 0 | J141: =IF(Assumptions!$C$45="Yes",J140-AVERAGE(J132,J135),J140-J132) -> 0
B142: Revolver commitment fee - % | F142: =Assumptions!$K$37 -> 0.0075 | G142: =Assumptions!$K$37 -> 0.0075 | H142: =Assumptions!$K$37 -> 0.0075 | I142: =Assumptions!$K$37 -> 0.0075 | J142: =Assumptions!$K$37 -> 0.0075
...

Sheet Loan Terms Derivation
B2: SOFR RATE | C2: 0.0424
B4: Revolver
B6: Spread over SOFR (bps) | C6: 200 | E6: revolver line of credit from 2022 holds 150-250 bps over SOFR
B8: Interest rate | C8: =$C$2+C6/10000 -> 0.0624
B10: Commitment fee | C10: 0.0075 | E10: choosing a midpoint in the typical 0.25-1.0%
B12: TLA
B14: Spread over SOFR (bps) | C14: 236 | E14: BofA High Yield Index Effective Yield - B
B16: Interest rate | C16: =$C$2+C14/10000 -> 0.066
B18: Beginning principal | C18: =Assumptions!D38 -> 964
B19: Amortization length (yrs) | C19: 5 | E19: * assuming fully amortizing by 2029
B20: Annual principle repayment | C20: =C18/C19 -> 192.8
B22: TLB
B24: Spread over SOFR (bps) | C24: =C14 -> 236 | E24: * assuming TLA spread = TLB spread
B26: Interest rate | C26: =$C$2+C24/10000 -> 0.066
B28: Mandatory amortization | C28: 0.02
B30: High Yield
B32: Spread over term loan | C32: 300 | E32: BofA High Yield Effective Yield Index
B34: Interest rate | C34: =$C$16+C32/10000 -> 0.096
B36: Mezzanine
B38: Spread over SOFR | C38: 925 | E38: reference shows 925-bp OAS spread for mezz debt - BB
B40: PIK interest rate | C40: 0.02
B41: Interest rate ( -PIK ) | C41: =C38/10000+C2-C40 -> 0.1149
B42: Total interest rate | C42: =SUM(C40:C41) -> 0.1349

Sheet Tax Schedules 
B2: $ millions
C3: 2022A | D3: 2023A | E3: 2024A | F3: 2025E | G3: 2026E | H3: 2027E | I3: 2028E | J3: 2029E
B5: Deferred Tax Assets & Liabilities Schedule
B7: Net operating loss | C7: 65 | D7: 59 | E7: 53 | F7: ='Tax Schedules '!F62 -> 49.067895 | G7: ='Tax Schedules '!G62 -> 30.070145 | H7: ='Tax Schedules '!H62 -> 6.014029 | I7: ='Tax Schedules '!I62 -> 1.2028058 | J7: ='Tax Schedules '!J62 -> 0.24056116
B8: Operating lease liabilities | C8: 81 | D8: 90 | E8: 97 | F8: =MAX(0,E8-F29) -> 80.833333 | G8: =MAX(0,F8-G29) -> 64.666667 | H8: =MAX(0,G8-H29) -> 48.5 | I8: =MAX(0,H8-I29) -> 32.333333 | J8: =MAX(0,I8-J29) -> 16.166667
B9: PP&E | C9: 5 | D9: 5 | E9: 0 | F9: =MAX(0,E9) -> 0 | G9: =MAX(0,F9) -> 0 | H9: =MAX(0,G9) -> 0 | I9: =MAX(0,H9) -> 0 | J9: =MAX(0,I9) -> 0 | M9: Item | N9: Unwind (yrs)
B10: Equity-based compensation | C10: 2 | D10: 1 | E10: 1 | F10: =MAX(0,E10-F32) -> 0 | G10: =MAX(0,F10-G32) -> 0 | H10: =MAX(0,G10-H32) -> 0 | I10: =MAX(0,H10-I32) -> 0 | J10: =MAX(0,I10-J32) -> 0 | M10: Op. Leases | N10: 6
B11: Other | C11: 5 | D11: 6 | E11: 6 | F11: =MAX(0,E11-F31) -> 4.8 | G11: =MAX(0,F11-G31) -> 3.6 | H11: =MAX(0,G11-H31) -> 2.4 | I11: =MAX(0,H11-I31) -> 1.2 | J11: =MAX(0,I11-J31) -> 0 | M11: PP&E | N11: =Assumptions!C51 -> 10
B12: Valuation allowance | C12: -88 | D12: -84 | E12: 0 | F12: =E12 -> 0 | G12: =F12 -> 0 | H12: =G12 -> 0 | I12: =H12 -> 0 | J12: =I12 -> 0 | M12: Other | N12: 5
B13: Interest carryfoward | C13: =C76 -> 0 | D13: =D76 -> 0 | E13: =E76 -> 0 | F13: =F76 -> 102.84299 | G13: =G76 -> 205.2104 | H13: =H76 -> 304.6989 | I13: =I76 -> 400.93087 | J13: =J76 -> 493.66128 | M13: Equity Comp | N13: 1
B14: Deferred tax asset, net | C14: =SUM(C7:C13) -> 70 | D14: =SUM(D7:D13) -> 77 | E14: =SUM(E7:E13) -> 157 | F14: =SUM(F7:F13) -> 237.54422 | G14: =SUM(G7:G13) -> 303.54721 | H14: =SUM(H7:H13) -> 361.61293 | I14: =SUM(I7:I13) -> 435.667 | J14: =SUM(J7:J13) -> 510.06851
B16: Operating lease assets | C16: -71 | D16: -77 | E16: -82 | F16: =MIN(0,E16-F30) -> -68.333333 | G16: =MIN(0,F16-G30) -> -54.666667 | H16: =MIN(0,G16-H30) -> -41 | I16: =MIN(0,H16-I30) -> -27.333333 | J16: =MIN(0,I16-J30) -> -13.666667
B17: PP&E | C17: 0 | D17: 0 | E17: -3 | F17: =MIN(0,E17-F28) -> -2.7 | G17: =MIN(0,F17-G28) -> -2.4 | H17: =MIN(0,G17-H28) -> -2.1 | I17: =MIN(0,H17-I28) -> -1.8 | J17: =MIN(0,I17-J28) -> -1.5
B18: New PP&E DTL | C18: 0 | D18: 0 | E18: =-Schedules!C15 -> -125.45997 | F18: =MIN(0,E18-F27) -> -112.91398 | G18: =MIN(0,F18-G27) -> -100.36798 | H18: =MIN(0,G18-H27) -> -87.821981 | I18: =MIN(0,H18-I27) -> -75.275984 | J18: =MIN(0,I18-J27) -> -62.729987
B19: Deferred tax liability, net | C19: =SUM(C16:C18) -> -71 | D19: =SUM(D16:D18) -> -77 | E19: =SUM(E16:E18) -> -210.45997 | F19: =SUM(F16:F18) -> -183.94731 | G19: =SUM(G16:G18) -> -157.43465 | H19: =SUM(H16:H18) -> -130.92198 | I19: =SUM(I16:I18) -> -104.40932 | J19: =SUM(J16:J18) -> -77.896653
B21: Total net deferred tax assets (liabilities) | C21: =C14+C19 -> -1 | D21: =D14+D19 -> 0 | E21: =E14+E19 -> -53.459973 | F21: =F14+F19 -> 53.596913 | G21: =G14+G19 -> 146.11257 | H21: =H14+H19 -> 230.69094 | I21: =I14+I19 -> 331.25769 | J21: =J14+J19 -> 432.17185
B22: ∆ Total net DTA (DTL) | F22: =F21-E21 -> 107.05689 | G22: =G21-F21 -> 92.515654 | H22: =H21-G21 -> 84.578377 | I22: =I21-H21 -> 100.56674 | J22: =J21-I21 -> 100.91417
B24: Balance sheet deferred tax assets | C24: =IF(C21<0,0,C21) -> 0 | D24: =IF(D21<0,0,D21) -> 0 | E24: =IF(E21<0,0,E21) -> 0 | F24: =IF(F21<0,0,F21) -> 53.596913 | G24: =IF(G21<0,0,G21) -> 146.11257 | H24: =IF(H21<0,0,H21) -> 230.69094 | I24: =IF(I21<0,0,I21) -> 331.25769 | J24: =IF(J21<0,0,J21) -> 432.17185
B25: Balance sheet deferred tax liabilities | C25: =IF(C21<0,-C21,0) -> 1 | D25: =IF(D21<0,-D21,0) -> 0 | E25: =IF(E21<0,-E21,0) -> 53.459973 | F25: =IF(F21<0,-F21,0) -> 0 | G25: =IF(G21<0,-G21,0) -> 0 | H25: =IF(H21<0,-H21,0) -> 0 | I25: =IF(I21<0,-I21,0) -> 0 | J25: =IF(J21<0,-J21,0) -> 0
B27: New PP&E DTL unwind | F27: =-Schedules!$C$16 -> -12.545997 | G27: =-Schedules!$C$16 -> -12.545997 | H27: =-Schedules!$C$16 -> -12.545997 | I27: =-Schedules!$C$16 -> -12.545997 | J27: =-Schedules!$C$16 -> -12.545997
B28: Old PP&E unwind | F28: =$E$17/$N$11 -> -0.3 | G28: =$E$17/$N$11 -> -0.3 | H28: =$E$17/$N$11 -> -0.3 | I28: =$E$17/$N$11 -> -0.3 | J28: =$E$17/$N$11 -> -0.3
B29: Operating lease liabilities unwind | F29: =$E$8/$N$10 -> 16.166667 | G29: =$E$8/$N$10 -> 16.166667 | H29: =$E$8/$N$10 -> 16.166667 | I29: =$E$8/$N$10 -> 16.166667 | J29: =$E$8/$N$10 -> 16.166667
B30: Operating lease assets unwind | F30: =$E$16/$N$10 -> -13.666667 | G30: =$E$16/$N$10 -> -13.666667 | H30: =$E$16/$N$10 -> -13.666667 | I30: =$E$16/$N$10 -> -13.666667 | J30: =$E$16/$N$10 -> -13.666667
B31: Other | F31: =$E$11/$N$12 -> 1.2 | G31: =$E$11/$N$12 -> 1.2 | H31: =$E$11/$N$12 -> 1.2 | I31: =$E$11/$N$12 -> 1.2 | J31: =$E$11/$N$12 -> 1.2
B32: Equity based comp | F32: =$E$10/$N$13 -> 1 | G32: 0 | H32: 0 | I32: 0 | J32: 0
B34: Tax Schedule
B36: Income tax expense (benefit) at statutory rate | C36: -12 | D36: 3 | E36: 13 | F36: =F45*Assumptions!$C$27 -> -84.354756 | G36: =G45*Assumptions!$C$27 -> -69.795685 | H36: =H45*Assumptions!$C$27 -> -52.416092 | I36: =I45*Assumptions!$C$27 -> -32.633651 | J36: =J45*Assumptions!$C$27 -> -10.34819
B37: State income tax expense (benefit) | C37: -2 | D37: 1 | E37: 6 | F37: =$N$40*F45 -> -27.492537 | G37: =$N$40*G45 -> -22.747508 | H37: =$N$40*H45 -> -17.083226 | I37: =$N$40*I45 -> -10.635819 | J37: =$N$40*J45 -> -3.3726375
B38: (Decrease) increase in valuation allowance | C38: 13 | D38: -5 | E38: -84 | F38: 0 | G38: 0 | H38: 0 | I38: 0 | J38: 0 | N38: Stat. Rate
B39: Deferred taxes | C39: 1 | D39: 1 | E39: 0 | F39: ='Financial Statements'!F33 -> 0 | G39: ='Financial Statements'!G33 -> 0 | H39: ='Financial Statements'!H33 -> 0 | I39: ='Financial Statements'!I33 -> 0 | J39: ='Financial Statements'!J33 -> 0 | M39: Federal | N39: 0.21
B40: Equity based compensation | C40: 0 | D40: 0 | E40: -5 | F40: 0 | G40: 0 | H40: 0 | I40: 0 | J40: 0 | M40: State | N40: {=AVERAGE(C37:E37/C45:E45)} -> 0.068442292
B41: Nondeductible executive compensation | C41: 0 | D41: 1 | E41: 0 | F41: 0 | G41: 0 | H41: 0 | I41: 0 | J41: 0 | M41: Total Stat. | N41: =N39+(1-N39)*N40 -> 0.26406941
B42: Permanent adjustments | C42: 0 | D42: 0 | E42: 0 | F42: 0 | G42: 0 | H42: 0 | I42: 0 | J42: 0
B43: (Benefit from) provision for income taxes | C43: =SUM(C36:C42) -> 0 | D43: =SUM(D36:D42) -> 1 | E43: =SUM(E36:E42) -> -70 | F43: =SUM(F36:F42) -> -111.84729 | G43: =SUM(G36:G42) -> -92.543193 | H43: =SUM(H36:H42) -> -69.499318 | I43: =SUM(I36:I42) -> -43.26947 | J43: =SUM(J36:J42) -> -13.720828
B45: Earnings before tax (EBT) | C45: ='Financial Statements'!C113 -> -59 | D45: ='Financial Statements'!D113 -> 14 | E45: ='Financial Statements'!E113 -> 60 | F45: ='Financial Statements'!F113 -> -401.68931 | G45: ='Financial Statements'!G113 -> -332.36041 | H45: ='Financial Statements'!H113 -> -249.60044 | I45: ='Financial Statements'!I113 -> -155.39834 | J45: ='Financial Statements'!J113 -> -49.277097
B46: Taxable income (w/ net DTA/DTL unwind) | C46: =C36/$N$39 -> -57.142857 | D46: =D36/$N$39 -> 14.285714 | E46: =E36/$N$39 -> 61.904762 | F46: =F45+SUM(F38:F42)+F70-SUM(F27:F32)/$N$41 -> 18.613027 | G46: =G45+SUM(G38:G42)+G70-SUM(G27:G32)/$N$41 -> 89.927824 | H46: =H45+SUM(H38:H42)+H70-SUM(H27:H32)/$N$41 -> 161.78569 | I46: =I45+SUM(I38:I42)+I70-SUM(I27:I32)/$N$41 -> 243.65571 | J46: =J45+SUM(J38:J42)+J70-SUM(J27:J32)/$N$41 -> 336.51696 | L46: * assuming straight-line depreciation for tax purposes
B47: Applicable NOLs | F47: =IF(F46>0,MIN(0.8*F59/$N$41,0.8*F46),0) -> 14.890422 | G47: =IF(G46>0,MIN(0.8*G59/$N$41,0.8*G46),0) -> 71.942259 | H47: =IF(H46>0,MIN(0.8*H59/$N$41,0.8*H46),0) -> 91.097701 | I47: =IF(I46>0,MIN(0.8*I59/$N$41,0.8*I46),0) -> 18.21954 | J47: =IF(J46>0,MIN(0.8*J59/$N$41,0.8*J46),0) -> 3.643908
B48: Taxable income after NOL | F48: =F46-F47 -> 3.7226054 | G48: =G46-G47 -> 17.985565 | H48: =H46-H47 -> 70.68799 | I48: =I46-I47 -> 225.43617 | J48: =J46-J47 -> 332.87305
B50: Current tax (expense) benefit | F50: =-F48*$N$41 -> -0.98302621 | G50: =-G48*$N$41 -> -4.7494375 | H50: =-H48*$N$41 -> -18.666536 | I50: =-I48*$N$41 -> -59.530796 | J50: =-J48*$N$41 -> -87.901591
B52: Alternative minimum tax (if AFSI > 0) | F52: =IF(F45>0,F45*0.15,0) -> 0 | G52: =IF(G45>0,G45*0.15,0) -> 0 | H52: =IF(H45>0,H45*0.15,0) -> 0 | I52: =IF(I45>0,I45*0.15,0) -> 0 | J52: =IF(J45>0,J45*0.15,0) -> 0
B54: NOL Schedule
B56: Total statutory tax expense (benefit) | C56: =SUM(C36:C37) -> -14 | D56: =SUM(D36:D37) -> 4 | E56: =SUM(E36:E37) -> 19 | F56: =F45*$N$41 -> -106.07386 | G56: =G45*$N$41 -> -87.766217 | H56: =H45*$N$41 -> -65.911841 | I56: =I45*$N$41 -> -41.035948 | J56: =J45*$N$41 -> -13.012574
B57: Effect to NOL | F57: =IF(F56+F71<=F59,F56+F71,F59) -> -3.2308663 | G57: =IF(G56+G71<=G59,G56+G71,G59) -> 14.60119 | H57: =IF(H56+H71<=H59,H56+H71,H59) -> 30.070145 | I57: =IF(I56+I71<=I59,I56+I71,I59) -> 6.014029 | J57: =IF(J56+J71<=J59,J56+J71,J59) -> 1.2028058 | L57: * assuming NOLs generated post 2017 (TCJA)
B59: Beginning NOL credit | D59: =C62 -> 65 | E59: =D62 -> 59 | F59: =E62 -> 53 | G59: =F62 -> 49.067895 | H59: =G62 -> 30.070145 | I59: =H62 -> 6.014029 | J59: =I62 -> 1.2028058
B60: NOL increase | D60: 0 | E60: 0 | F60: =IF(F50>0,F50,0) -> 0 | G60: =IF(G50>0,G50,0) -> 0 | H60: =IF(H50>0,H50,0) -> 0 | I60: =IF(I50>0,I50,0) -> 0 | J60: =IF(J50>0,J50,0) -> 0
B61: NOL decrease | D61: =-(D62-D59) -> 6 | E61: =-(E62-E59) -> 6 | F61: =-IF(F47>0,F47*$N$41,0) -> -3.9321048 | G61: =-IF(G47>0,G47*$N$41,0) -> -18.99775 | H61: =-IF(H47>0,H47*$N$41,0) -> -24.056116 | I61: =-IF(I47>0,I47*$N$41,0) -> -4.8112232 | J61: =-IF(J47>0,J47*$N$41,0) -> -0.96224465
B62: Ending NOL credit | C62: ='Tax Schedules '!C7 -> 65 | D62: ='Tax Schedules '!D7 -> 59 | E62: ='Tax Schedules '!E7 -> 53 | F62: =SUM(F59:F61) -> 49.067895 | G62: =SUM(G59:G61) -> 30.070145 | H62: =SUM(H59:H61) -> 6.014029 | I62: =SUM(I59:I61) -> 1.2028058 | J62: =SUM(J59:J61) -> 0.24056116
B64: Interest Carryforward Schedule
B66: Earnings before interest & tax (EBIT) | C66: ='Financial Statements'!C109 -> -60 | D66: ='Financial Statements'!D109 -> 5 | E66: ='Financial Statements'!E109 -> 43 | F66: ='Financial Statements'!F109 -> -12.234913 | G66: ='Financial Statements'!G109 -> 78.990001 | H66: ='Financial Statements'!H109 -> 181.6441 | I66: ='Financial Statements'!I109 -> 298.60126 | J66: ='Financial Statements'!J109 -> 431.2602
B67: Gross interest | F67: ='Ratios & Statistics'!F28 -> 389.4544 | G67: ='Ratios & Statistics'!G28 -> 411.35041 | H67: ='Ratios & Statistics'!H28 -> 431.24454 | I67: ='Ratios & Statistics'!I28 -> 453.9996 | J67: ='Ratios & Statistics'!J28 -> 480.5373 | L67: * assuming that ATI ≈ EBIT for business interest deduction calculation
B68: Business interest deduction limit | F68: =IF(F66<0,0,F66*0.3) -> 0 | G68: =IF(G66<0,0,G66*0.3) -> 23.697 | H68: =IF(H66<0,0,H66*0.3) -> 54.493229 | I68: =IF(I66<0,0,I66*0.3) -> 89.580379 | J68: =IF(J66<0,0,J66*0.3) -> 129.37806
B69: Interest deduction for tax | F69: =MIN(F67,F68) -> 0 | G69: =MIN(G67,G68) -> 23.697 | H69: =MIN(H67,H68) -> 54.493229 | I69: =MIN(I67,I68) -> 89.580379 | J69: =MIN(J67,J68) -> 129.37806
B70: Interest carryforward created | F70: =F67-F69 -> 389.4544 | G70: =G67-G69 -> 387.65341 | H70: =H67-H69 -> 376.75131 | I70: =I67-I69 -> 364.41922 | J70: =J67-J69 -> 351.15924
B71: Tax benefit (Expense) of interest carryforward | F71: =F70*$N$41 -> 102.84299 | G71: =G70*$N$41 -> 102.36741 | H71: =H70*$N$41 -> 99.488496 | I71: =I70*$N$41 -> 96.23197 | J71: =J70*$N$41 -> 92.730413
B73: Beginning interest carryforward credit | D73: =C76 -> 0 | E73: =D76 -> 0 | F73: =E76 -> 0 | G73: =F76 -> 102.84299 | H73: =G76 -> 205.2104 | I73: =H76 -> 304.6989 | J73: =I76 -> 400.93087
B74: IC increase | F74: =IF(F71>0,F71,0) -> 102.84299 | G74: =IF(G71>0,G71,0) -> 102.36741 | H74: =IF(H71>0,H71,0) -> 99.488496 | I74: =IF(I71>0,I71,0) -> 96.23197 | J74: =IF(J71>0,J71,0) -> 92.730413
B75: IC decrease | F75: =-IF(F71<0,MIN(-F71,F73),0) -> 0 | G75: =-IF(G71<0,MIN(-G71,G73),0) -> 0 | H75: =-IF(H71<0,MIN(-H71,H73),0) -> 0 | I75: =-IF(I71<0,MIN(-I71,I73),0) -> 0 | J75: =-IF(J71<0,MIN(-J71,J73),0) -> 0
B76: Ending interest carryforward credit | C76: 0 | D76: =SUM(D73:D75) -> 0 | E76: =SUM(E73:E75) -> 0 | F76: =SUM(F73:F75) -> 102.84299 | G76: =SUM(G73:G75) -> 205.2104 | H76: =SUM(H73:H75) -> 304.6989 | I76: =SUM(I73:I75) -> 400.93087 | J76: =SUM(J73:J75) -> 493.66128

Sheet Exit Waterfall
B2: Exit Multiple Derivation
B4: Company Comp | C4: Revenue | D4: mcap | E4: Total Debt | F4: Cash | G4: Preferred/MI | H4: Lease Liab. | I4: EV | J4: EV / Rev | N4: COMP Y/N | O4: Why
B5: #VALUE! | C5: 11314 | D5: {=_FV(B5,"Market cap",TRUE)/1000000} -> 40435.261 | E5: 0 | F5: 749 | G5: 0 | H5: 4510 | I5: =D5+E5-F5+G5+H5 -> 44196.261 | J5: =I5/C5 -> 3.9063339 | L5: CMG 10K | N5: Y | O5: great comp
B6: #VALUE! | C6: 7549 | D6: {=_FV(B6,"Market cap",TRUE)/1000000} -> 40967.045 | E6: 11333 | F6: 616 | G6: 0 | H6: 1020 | I6: =D6+E6-F6+G6+H6 -> 52704.045 | J6: =I6/C6 -> 6.9815929 | L6: YUM 10K | N6: N | O6: franchised
B7: #VALUE! | C7: 1253 | D7: {=_FV(B7,"Market cap",TRUE)/1000000} -> 3923.0621 | E7: =247 -> 247 | F7: 321 | G7: 24 | H7: 550 | I7: =D7+E7-F7+G7+H7 -> 4423.0621 | J7: =I7/C7 -> 3.5299778 | L7: SHAK 10K | N7: N | O7: franchised international
B8: #VALUE! | C8: 36176 | D8: {=_FV(B8,"Market cap",TRUE)/1000000} -> 93475.918 | E8: 14320 | F8: 3286 | G8: 7 | H8: 10235 | I8: =D8+E8-F8+G8+H8 -> 114751.92 | J8: =I8/C8 -> 3.1720455 | L8: SBUX 10K | N8: N | O8: slow growth
B9: #VALUE! | C9: 25920 | D9: {=_FV(B9,"Market cap",TRUE)/1000000} -> 213025.19 | E9: 38424 | F9: 1085 | G9: 0 | H9: 3524 | I9: =D9+E9-F9+G9+H9 -> 253888.19 | J9: =I9/C9 -> 9.7950689 | L9: MCD 10K | N9: N | O9: franchised
B11: Exit Waterfall
B13: 2029 revenue | C13: ='Financial Statements'!J84 -> 2586.6235
B14: Exit multiple (EV / Rev) | C14: =J5 -> 3.9063339
B15: Enterprise value | C15: =C13*C14 -> 10104.215
B16: - Debt | C16: =-'Ratios & Statistics'!J24 -> -6125.5015
B17: + Balance sheet cash | C17: ='Financial Statements'!J10 -> 100
B18: + Cash from option exercise
B19: Equity value | C19: =SUM(C15:C18) -> 4078.7135
B21: Sponsor equity | C21: ='Sources & Uses'!C16 -> 1364.998
B22: Management rollover | C22: ='Sources & Uses'!C17 -> 151.66645
B23: Management options | C23: =SUM(C21:C22)*Assumptions!C31 -> 151.66645
B24: Total shareholdings | C24: =SUM(C21:C23) -> 1668.3309
B26: Sponsor equity - % | C26: =C21/$C$24 -> 0.81818182
B27: Management rollover - % | C27: =C22/$C$24 -> 0.090909091
B28: Management options - % | C28: =C23/$C$24 -> 0.090909091
B29: Total Shareholdings - % | C29: =SUM(C26:C28) -> 1
B31: Exit proceeds
B33: Sponsor equity | C33: =C26*$C$19 -> 3337.1292
B34: Management rollover | C34: =C27*$C$19 -> 370.79213
B35: Management options | C35: =C28*$C$19 -> 370.79213
B36: Total shareholder proceeds | C36: =SUM(C33:C35) -> 4078.7135
B38: Sponsor IRR & MoIC
B40: Year | C40: 0 | D40: 1 | E40: 2 | F40: 3 | G40: 4 | H40: 5
B41: Cash flow to sponsor | C41: =-C21 -> -1364.998 | D41: 0 | E41: 0 | F41: 0 | G41: 0 | H41: =C33 -> 3337.1292
B43: IRR | C43: =IRR(C41:H41) -> 0.1957715
B44: MoIC | C44: =H41/-C41 -> 2.4447868

Sheet Ratios & Statistics
B2: $ millions
C3: 2022A | D3: 2023A | E3: 2024A | F3: 2025E | G3: 2026E | H3: 2027E | I3: 2028E | J3: 2029E
B5: Income Statement Statistics
B7: Revenue growth | C7: 0 | D7: ='Financial Statements'!D84/'Financial Statements'!C84-1 -> 0.29255319 | E7: ='Financial Statements'!E84/'Financial Statements'!D84-1 -> 0.3223594 | F7: ='Financial Statements'!F84/'Financial Statements'!E84-1 -> 0.26707084 | G7: ='Financial Statements'!G84/'Financial Statements'!F84-1 -> 0.24482759 | H7: ='Financial Statements'!H84/'Financial Statements'!G84-1 -> 0.21433518 | I7: ='Financial Statements'!I84/'Financial Statements'!H84-1 -> 0.19209581 | J7: ='Financial Statements'!J84/'Financial Statements'!I84-1 -> 0.17515823
B8: COGS - % of revenue | C8: ='Financial Statements'!C90/-'Financial Statements'!C84 -> 0.82624113 | D8: ='Financial Statements'!D90/-'Financial Statements'!D84 -> 0.75171468 | E8: ='Financial Statements'!E90/-'Financial Statements'!E84 -> 0.74896266 | F8: =-'Financial Statements'!F90/'Financial Statements'!F84 -> 0.71570362 | G8: =-'Financial Statements'!G90/'Financial Statements'!G84 -> 0.70204342 | H8: =-'Financial Statements'!H90/'Financial Statements'!H84 -> 0.6890337 | I8: =-'Financial Statements'!I90/'Financial Statements'!I84 -> 0.6766435 | J8: =-'Financial Statements'!J90/'Financial Statements'!J84 -> 0.66484331
B9: SG&A - % of revenue | C9: ='Financial Statements'!C97/-'Financial Statements'!C84 -> 0.13475177 | D9: ='Financial Statements'!D97/-'Financial Statements'!D84 -> 0.14677641 | E9: ='Financial Statements'!E97/-'Financial Statements'!E84 -> 0.12551867 | F9: =-'Financial Statements'!F97/'Financial Statements'!F84 -> 0.12149383 | G9: =-'Financial Statements'!G97/'Financial Statements'!G84 -> 0.10986 | H9: =-'Financial Statements'!H97/'Financial Statements'!H84 -> 0.099655764 | I9: =-'Financial Statements'!I97/'Financial Statements'!I84 -> 0.091243865 | J9: =-'Financial Statements'!J97/'Financial Statements'!J84 -> 0.084147035
B10: D&A - % of revenue | C10: =-'Financial Statements'!C107/'Financial Statements'!C84 -> 0.076241135 | D10: =-'Financial Statements'!D107/'Financial Statements'!D84 -> 0.065843621 | E10: =-'Financial Statements'!E107/'Financial Statements'!E84 -> 0.063278008 | F10: =-'Financial Statements'!F107/'Financial Statements'!F84 -> 0.17281921 | G10: =-'Financial Statements'!G107/'Financial Statements'!G84 -> 0.13614665 | H10: =-'Financial Statements'!H107/'Financial Statements'!H84 -> 0.11293308 | I10: =-'Financial Statements'!I107/'Financial Statements'!I84 -> 0.096451713 | J10: =-'Financial Statements'!J107/'Financial Statements'!J84 -> 0.084282573
B11: Interest - % of revenue | C11: =-'Financial Statements'!C111/'Financial Statements'!C84 -> -0.0017730496 | D11: =-'Financial Statements'!D111/'Financial Statements'!D84 -> -0.012345679 | E11: =-'Financial Statements'!E111/'Financial Statements'!E84 -> -0.017634855 | F11: =-'Financial Statements'!F111/'Financial Statements'!F84 -> 0.31884432 | G11: =-'Financial Statements'!G111/'Financial Statements'!G84 -> 0.27053583 | H11: =-'Financial Statements'!H111/'Financial Statements'!H84 -> 0.23355969 | I11: =-'Financial Statements'!I111/'Financial Statements'!I84 -> 0.2062617 | J11: =-'Financial Statements'!J111/'Financial Statements'!J84 -> 0.18577783
B12: Effective tax rate | C12: =-'Financial Statements'!C115/'Financial Statements'!C84 -> 0 | D12: =-'Financial Statements'!D115/'Financial Statements'!D84 -> 0.0013717421 | E12: =-'Financial Statements'!E115/'Financial Statements'!E84 -> -0.072614108 | F12: =-'Financial Statements'!F115/'Financial Statements'!F113 -> 0.26406941 | G12: =-'Financial Statements'!G115/'Financial Statements'!G113 -> 0.26406941 | H12: =-'Financial Statements'!H115/'Financial Statements'!H113 -> 0.26406941 | I12: =-'Financial Statements'!I115/'Financial Statements'!I113 -> 0.26406941 | J12: =-'Financial Statements'!J115/'Financial Statements'!J113 -> 0.26406941
B14: Margins
B16: Gross margin | C16: ='Financial Statements'!C92/'Financial Statements'!C84 -> 0.17375887 | D16: ='Financial Statements'!D92/'Financial Statements'!D84 -> 0.24828532 | E16: ='Financial Statements'!E92/'Financial Statements'!E84 -> 0.25103734 | F16: ='Financial Statements'!F92/'Financial Statements'!F84 -> 0.28429638 | G16: ='Financial Statements'!G92/'Financial Statements'!G84 -> 0.29795658 | H16: ='Financial Statements'!H92/'Financial Statements'!H84 -> 0.3109663 | I16: ='Financial Statements'!I92/'Financial Statements'!I84 -> 0.3233565 | J16: ='Financial Statements'!J92/'Financial Statements'!J84 -> 0.33515669
B17: EBITDA margin | C17: ='Financial Statements'!C101/'Financial Statements'!C84 -> -0.030141844 | D17: ='Financial Statements'!D101/'Financial Statements'!D84 -> 0.072702332 | E17: ='Financial Statements'!E101/'Financial Statements'!E84 -> 0.10788382 | F17: ='Financial Statements'!F101/'Financial Statements'!F84 -> 0.16280255 | G17: ='Financial Statements'!G101/'Financial Statements'!G84 -> 0.18809658 | H17: ='Financial Statements'!H101/'Financial Statements'!H84 -> 0.21131053 | I17: ='Financial Statements'!I101/'Financial Statements'!I84 -> 0.23211264 | J17: ='Financial Statements'!J101/'Financial Statements'!J84 -> 0.25100966
B18: EBIT margin | C18: ='Financial Statements'!C109/'Financial Statements'!C84 -> -0.10638298 | D18: ='Financial Statements'!D109/'Financial Statements'!D84 -> 0.0068587106 | E18: ='Financial Statements'!E109/'Financial Statements'!E84 -> 0.044605809 | F18: ='Financial Statements'!F109/'Financial Statements'!F84 -> -0.01001666 | G18: ='Financial Statements'!G109/'Financial Statements'!G84 -> 0.051949932 | H18: ='Financial Statements'!H109/'Financial Statements'!H84 -> 0.098377453 | I18: ='Financial Statements'!I109/'Financial Statements'!I84 -> 0.13566092 | J18: ='Financial Statements'!J109/'Financial Statements'!J84 -> 0.16672709
B19: EBT margin | C19: ='Financial Statements'!C113/'Financial Statements'!C84 -> -0.10460993 | D19: ='Financial Statements'!D113/'Financial Statements'!D84 -> 0.01920439 | E19: ='Financial Statements'!E113/'Financial Statements'!E84 -> 0.062240664 | F19: ='Financial Statements'!F113/'Financial Statements'!F84 -> -0.32886098 | G19: ='Financial Statements'!G113/'Financial Statements'!G84 -> -0.2185859 | H19: ='Financial Statements'!H113/'Financial Statements'!H84 -> -0.13518224 | I19: ='Financial Statements'!I113/'Financial Statements'!I84 -> -0.07060078 | J19: ='Financial Statements'!J113/'Financial Statements'!J84 -> -0.019050742
B20: Profit margin | C20: ='Financial Statements'!C117/'Financial Statements'!C84 -> -0.10460993 | D20: ='Financial Statements'!D117/'Financial Statements'!D84 -> 0.017832647 | E20: ='Financial Statements'!E117/'Financial Statements'!E84 -> 0.13485477 | F20: ='Financial Statements'!F117/'Financial Statements'!F84 -> -0.24201885 | G20: ='Financial Statements'!G117/'Financial Statements'!G84 -> -0.16086405 | H20: ='Financial Statements'!H117/'Financial Statements'!H84 -> -0.099484744 | I20: ='Financial Statements'!I117/'Financial Statements'!I84 -> -0.051957274 | J20: ='Financial Statements'!J117/'Financial Statements'!J84 -> -0.014020024
B22: Total Debt Statistics
B24: Total debt | F24: =Schedules!F200+Schedules!F185+Schedules!F171+Schedules!F156+Schedules!F135 -> 5170.6576 | G24: =Schedules!G200+Schedules!G185+Schedules!G171+Schedules!G156+Schedules!G135 -> 5489.5363 | H24: =Schedules!H200+Schedules!H185+Schedules!H171+Schedules!H156+Schedules!H135 -> 5752.8346 | I24: =Schedules!I200+Schedules!I185+Schedules!I171+Schedules!I156+Schedules!I135 -> 5973.6723 | J24: =Schedules!J200+Schedules!J185+Schedules!J171+Schedules!J156+Schedules!J135 -> 6125.5015
B26: Total cash interest expense | F26: =Schedules!F203+Schedules!F188+Schedules!F159+Schedules!F138+Schedules!F174 -> 379.8144 | G26: =Schedules!G203+Schedules!G188+Schedules!G159+Schedules!G138+Schedules!G174 -> 401.51761 | H26: =Schedules!H203+Schedules!H188+Schedules!H159+Schedules!H138+Schedules!H174 -> 421.21508 | I26: =Schedules!I203+Schedules!I188+Schedules!I159+Schedules!I138+Schedules!I174 -> 443.76956 | J26: =Schedules!J203+Schedules!J188+Schedules!J159+Schedules!J138+Schedules!J174 -> 470.10265
B27: Total PIK interest expense | F27: =Schedules!F206 -> 9.64 | G27: =Schedules!G206 -> 9.8328 | H27: =Schedules!H206 -> 10.029456 | I27: =Schedules!I206 -> 10.230045 | J27: =Schedules!J206 -> 10.434646
B28: Total interest expense | F28: =SUM(F26:F27) -> 389.4544 | G28: =SUM(G26:G27) -> 411.35041 | H28: =SUM(H26:H27) -> 431.24454 | I28: =SUM(I26:I27) -> 453.9996 | J28: =SUM(J26:J27) -> 480.5373
B30: Total mandatory amortization | F30: =-Schedules!F129 -> 231.36 | G30: =-Schedules!G129 -> 230.5888 | H30: =-Schedules!H129 -> 240.62572 | I30: =-Schedules!I129 -> 249.54709 | J30: =-Schedules!J129 -> 249.50506
B32: Debt / equity | F32: =F24/'Financial Statements'!F46 -> 4.2346029 | G32: =G24/'Financial Statements'!G46 -> 5.621905 | H32: =H24/'Financial Statements'!H46 -> 7.2566596 | I32: =I24/'Financial Statements'!I46 -> 8.8054814 | J32: =J24/'Financial Statements'!J46 -> 9.5392096
B33: Debt / EBITDA | F33: =F24/'Financial Statements'!F101 -> 26.001994 | G33: =G24/'Financial Statements'!G101 -> 19.194094 | H33: =H24/'Financial Statements'!H101 -> 14.744669 | I33: =I24/'Financial Statements'!I101 -> 11.692456 | J33: =J24/'Financial Statements'!J101 -> 9.4344806

Sheet Sensitivity Analysis
C3: SOFR Rate | I3: Total Statutory Tax Rate
C5: 0.01 | D5: 0.02 | E5: 0.03 | F5: 0.04 | G5: 0.05 | I5: 0.2 | J5: 0.225 | K5: 0.25 | L5: 0.275 | M5: 0.3
B6: =Assumptions!G2 -> 0.1957715 | C6: 0.18792608 | D6: 0.17601042 | E6: 0.1627673 | F6: 0.14785602 | G6: 0.13111049 | I6: 0.1469152 | J6: 0.14635958 | K6: 0.14580289 | L6: 0.14524511 | M6: 0.14468625
C9: Purchase Premium Above Market | I9: Same Store Growth Rate
C11: 0.05 | D11: 0.1 | E11: 0.15 | F11: 0.2 | G11: 0.25 | I11: 0.01 | J11: 0.02 | K11: 0.03 | L11: 0.04 | M11: 0.05
B12: 0.10094048 | C12: 0.2191434 | D12: 0.18020618 | E12: 0.14774033 | F12: 0.12002115 | G12: 0.095916212 | I12: 0.12376527 | J12: 0.14774033 | K12: 0.17044729 | L12: 0.19205393 | M12: 0.21272633
C15: EV / Revenue Exit Multiple | I15: PMO Growth Rate
C17: 4 | D17: 4.5 | E17: 5 | F17: 5.5 | G17: 6 | I17: 0.01 | J17: 0.02 | K17: 0.03 | L17: 0.04 | M17: 0.05
C18: -0.010498665 | D18: 0.063623405 | E18: 0.12146681 | F18: 0.16937193 | G18: 0.21051129 | I18: 0.098345967 | J18: 0.12376527 | K18: 0.14774033 | L18: 0.17044729 | M18: 0.19205393
I21: Same Store Growth Rate
G23: 0.01 | H23: 0.02 | I23: 0.03 | J23: 0.04 | K23: 0.05
F24: 0.01 | G24: 0.06659113 | H24: 0.094432767 | I24: 0.12058932 | J24: 0.14519577 | K24: 0.1684445
F25: 0.02 | G25: 0.094432767 | H25: 0.12058932 | I25: 0.14519577 | J25: 0.1684445 | K25: 0.19052803
E26: PMO Growth | F26: 0.03 | G26: 0.12058932 | H26: 0.14519577 | I26: 0.1684445 | J26: 0.19052803 | K26: 0.21162246
F27: 0.04 | G27: 0.14519577 | H27: 0.1684445 | I27: 0.19052803 | J27: 0.21162246 | K27: 0.23176987
F28: 0.05 | G28: 0.1684445 | H28: 0.19052803 | I28: 0.21162246 | J28: 0.23176987 | K28: 0.25115286
